{"playlist_name": "Simone Young - Brahms: Sinfonie Nr. 2 - Tragische Ouvertüre",
"http_link": "http://open.spotify.com/user/ravelclaw/playlist/5RMZpLizAs94mftkbSIs74",
"spotify_link": "spotify:user:ravelclaw:playlist:5RMZpLizAs94mftkbSIs74",
"songs": [
{"name": "Symphony No. 2 in D major, Op. 73: I. Allegro non troppo", "artists": ["Simone Young", "Hamburg Philharmonic Orchestra"], "album": "Brahms: Sinfonie Nr. 2 - Tragische Ouvertüre", "duration": 1197000, "link": "spotify:track:2yQ7y1ZifvfVrL9Vk6vUzU"},
{"name": "Symphony No. 2 in D major, Op. 73: II. Adagio non troppo - L'istesso tempo, ma grazioso", "artists": ["Simone Young", "Hamburg Philharmonic Orchestra"], "album": "Brahms: Sinfonie Nr. 2 - Tragische Ouvertüre", "duration": 598000, "link": "spotify:track:47oFhC9GGqw1yDYqK7AC5n"},
{"name": "Symphony No. 2 in D major, Op. 73: III. Allegretto grazioso (quasi andantino) - Presto ma non assai", "artists": ["Simone Young", "Hamburg Philharmonic Orchestra"], "album": "Brahms: Sinfonie Nr. 2 - Tragische Ouvertüre", "duration": 301000, "link": "spotify:track:3ntqPDstH07Kr2S5wF31F2"},
{"name": "Symphony No. 2 in D major, Op. 73: IV. Allegro con spirito", "artists": ["Simone Young", "Hamburg Philharmonic Orchestra"], "album": "Brahms: Sinfonie Nr. 2 - Tragische Ouvertüre", "duration": 528000, "link": "spotify:track:5f7i4ckT4KIxU7TnWu0FOO"},
{"name": "Tragic Overture, Op. 81", "artists": ["Simone Young", "Hamburg Philharmonic Orchestra"], "album": "Brahms: Sinfonie Nr. 2 - Tragische Ouvertüre", "duration": 813000, "link": "spotify:track:7A6D13G8Y7UoG2eleRjASu"},
]}
