{"playlist_name": "Jeff Buckley",
"http_link": "http://open.spotify.com/user/ocramarco/playlist/1kYRQognJofq8wkns3USzA",
"spotify_link": "spotify:user:ocramarco:playlist:1kYRQognJofq8wkns3USzA",
"songs": [
{"name": "Last Goodbye", "artists": ["Jeff Buckley"], "album": "So Real: Songs From Jeff Buckley", "duration": 277000, "link": "spotify:track:3COJYs10WlQymS9ml663z2"},
{"name": "Lover, You Should've Come Over", "artists": ["Jeff Buckley"], "album": "So Real: Songs From Jeff Buckley", "duration": 402000, "link": "spotify:track:3sfEmuMx0Phhq76m5cEV9A"},
{"name": "Forget Her", "artists": ["Jeff Buckley"], "album": "So Real: Songs From Jeff Buckley", "duration": 310000, "link": "spotify:track:67UY4OaJlCFzcYowev7Q8d"},
{"name": "Eternal Life - Road Version", "artists": ["Jeff Buckley"], "album": "So Real: Songs From Jeff Buckley", "duration": 287000, "link": "spotify:track:3yaB7rk6rZo1QLUEoZ8gcm"},
{"name": "Dream Brother - (Alternate Take)", "artists": ["Jeff Buckley"], "album": "So Real: Songs From Jeff Buckley", "duration": 294000, "link": "spotify:track:3M9jHDWpajaa7idMfphRgD"},
{"name": "The Sky Is A Landfill", "artists": ["Jeff Buckley"], "album": "So Real: Songs From Jeff Buckley", "duration": 306000, "link": "spotify:track:7CEyUzdH62hotNbbf0MIqi"},
{"name": "Everybody Here Wants You", "artists": ["Jeff Buckley"], "album": "So Real: Songs From Jeff Buckley", "duration": 285000, "link": "spotify:track:3jXVgrmW3sLTJB2VVnWbmk"},
{"name": "So Real - Live And Acoustic in Japan", "artists": ["Jeff Buckley"], "album": "So Real: Songs From Jeff Buckley", "duration": 263000, "link": "spotify:track:1GXrm4CUqPUeJESzAcRyhi"},
{"name": "Mojo Pin - Live at Sin-é", "artists": ["Jeff Buckley"], "album": "So Real: Songs From Jeff Buckley", "duration": 318000, "link": "spotify:track:6SGJdiGj4A8RWpKYNzF6Si"},
{"name": "Vancouver", "artists": ["Jeff Buckley"], "album": "So Real: Songs From Jeff Buckley", "duration": 190000, "link": "spotify:track:4FTQf4vQlEVFFBQeuqe3fI"},
{"name": "Je N'en Connais Pas La Fin - Live At Sin-é", "artists": ["Jeff Buckley"], "album": "So Real: Songs From Jeff Buckley", "duration": 297000, "link": "spotify:track:01d5KPug84Re0vyndJCLFy"},
{"name": "Grace", "artists": ["Jeff Buckley"], "album": "So Real: Songs From Jeff Buckley", "duration": 323000, "link": "spotify:track:4zIYBKi1u2A3QoUexWx2wZ"},
{"name": "Hallelujah", "artists": ["Jeff Buckley"], "album": "So Real: Songs From Jeff Buckley", "duration": 415000, "link": "spotify:track:5qv0ohJV2QNwga79jLNDYQ"},
{"name": "I Know It's Over - Previously Unreleased", "artists": ["Jeff Buckley"], "album": "So Real: Songs From Jeff Buckley", "duration": 389000, "link": "spotify:track:50FR5YSqqH9wTVLW5ZjiW7"},
{"name": "Lover, You Should've Come Over - Previously Unreleased; Live", "artists": ["Jeff Buckley"], "album": "So Real: Songs From Jeff Buckley", "duration": 412000, "link": "spotify:track:380MhBrXwkscF7xwpillJt"},
{"name": "Mojo Pin", "artists": ["Jeff Buckley"], "album": "Grace", "duration": 343000, "link": "spotify:track:3mlurWDI0Bbxt78zbLTYWx"},
{"name": "Grace", "artists": ["Jeff Buckley"], "album": "Grace", "duration": 322000, "link": "spotify:track:3fBKIViWMcdN0UW8yFpNIt"},
{"name": "Last Goodbye", "artists": ["Jeff Buckley"], "album": "Grace", "duration": 275000, "link": "spotify:track:3vqz1pl7saLNHeVfQkme9O"},
{"name": "Lilac Wine", "artists": ["Jeff Buckley"], "album": "Grace", "duration": 272000, "link": "spotify:track:4aGwZg5cCtfdx6OmLRX76a"},
{"name": "So Real", "artists": ["Jeff Buckley"], "album": "Grace", "duration": 280000, "link": "spotify:track:5EWO2Pron8sXWZDVeSLRCN"},
{"name": "Hallelujah", "artists": ["Jeff Buckley"], "album": "Grace", "duration": 413000, "link": "spotify:track:47GcJDGbmlr9IZ8zwRgl7x"},
{"name": "Lover, You Should've Come Over", "artists": ["Jeff Buckley"], "album": "Grace", "duration": 403000, "link": "spotify:track:00zPocXDSLPVuvGEQZQI9T"},
{"name": "Corpus Christi Carol", "artists": ["Jeff Buckley"], "album": "Grace", "duration": 177000, "link": "spotify:track:4t2r0T1kMA5v55KFHHfydV"},
{"name": "Eternal Life", "artists": ["Jeff Buckley"], "album": "Grace", "duration": 293000, "link": "spotify:track:1n4qKTtKTVyZ9kn6cSF1Ni"},
{"name": "Dream Brother", "artists": ["Jeff Buckley"], "album": "Grace", "duration": 325000, "link": "spotify:track:6EAmq5lLxnlwuXPitlMOES"},
{"name": "Forget Her", "artists": ["Jeff Buckley"], "album": "Grace", "duration": 313000, "link": "spotify:track:57RZmr3YceDs3U5A6uMScA"},
{"name": "The Sky Is A Landfill", "artists": ["Jeff Buckley"], "album": "SKETCHES for My Sweetheart The Drunk", "duration": 309000, "link": "spotify:track:6uhQzWKkWp7fORpxqM3xyS"},
{"name": "Everybody Here Wants You", "artists": ["Jeff Buckley"], "album": "SKETCHES for My Sweetheart The Drunk", "duration": 285000, "link": "spotify:track:3ZiGB5u1rtoLeSoAeX1rKU"},
{"name": "Opened Once", "artists": ["Jeff Buckley"], "album": "SKETCHES for My Sweetheart The Drunk", "duration": 210000, "link": "spotify:track:561HOoegAAOySYsk2Ozl2p"},
{"name": "Nightmares By The Sea", "artists": ["Jeff Buckley"], "album": "SKETCHES for My Sweetheart The Drunk", "duration": 231000, "link": "spotify:track:4E8joeJ8Pei6Ds0dCNZaGn"},
{"name": "Yard Of Blonde Girls", "artists": ["Jeff Buckley"], "album": "SKETCHES for My Sweetheart The Drunk", "duration": 247000, "link": "spotify:track:4weJz5CYGrejDB7R8uDoJO"},
{"name": "Witches' Rave", "artists": ["Jeff Buckley"], "album": "SKETCHES for My Sweetheart The Drunk", "duration": 280000, "link": "spotify:track:6l9Wc0VPQR2NGuruiS3lC8"},
{"name": "New Year's Prayer", "artists": ["Jeff Buckley"], "album": "SKETCHES for My Sweetheart The Drunk", "duration": 278000, "link": "spotify:track:3BFpiZlx72SBGMy0vQQCMP"},
{"name": "Morning Theft", "artists": ["Jeff Buckley"], "album": "SKETCHES for My Sweetheart The Drunk", "duration": 220000, "link": "spotify:track:05xuYWgAuFSplvNoJOkU9X"},
{"name": "Vancouver", "artists": ["Jeff Buckley"], "album": "SKETCHES for My Sweetheart The Drunk", "duration": 193000, "link": "spotify:track:6UVKfC2wSE8o2MpF9AK9sB"},
{"name": "You & I", "artists": ["Jeff Buckley"], "album": "SKETCHES for My Sweetheart The Drunk", "duration": 338000, "link": "spotify:track:3WdpRR7iLZcZuxW5gAVsmo"},
{"name": "Nightmares By The Sea", "artists": ["Jeff Buckley"], "album": "SKETCHES for My Sweetheart The Drunk", "duration": 231000, "link": "spotify:track:3m5gn3VH2rF1VxoUWc4IVy"},
{"name": "New Year's Prayer", "artists": ["Jeff Buckley"], "album": "SKETCHES for My Sweetheart The Drunk", "duration": 250000, "link": "spotify:track:4rlH8XYDAaDPHLJYpxQT50"},
{"name": "Haven't You Heard", "artists": ["Jeff Buckley"], "album": "SKETCHES for My Sweetheart The Drunk", "duration": 246000, "link": "spotify:track:3lKq1GA9CaSNkfOffNX2Ec"},
{"name": "I Know We Could Be So Happy Baby (If We Wanted To Be)", "artists": ["Jeff Buckley"], "album": "SKETCHES for My Sweetheart The Drunk", "duration": 265000, "link": "spotify:track:0uCG2bm6p3hij6KOIBXhyy"},
{"name": "Murder Suicide Meteor Slave", "artists": ["Jeff Buckley"], "album": "SKETCHES for My Sweetheart The Drunk", "duration": 352000, "link": "spotify:track:5wIqQ7JC2hOSvBQhp6DaI5"},
{"name": "Back In N.Y.C.", "artists": ["Jeff Buckley"], "album": "SKETCHES for My Sweetheart The Drunk", "duration": 454000, "link": "spotify:track:6WkceHKgTHqe0u7PDwKY1I"},
{"name": "Gunshot Glitter", "artists": ["Jeff Buckley"], "album": "SKETCHES for My Sweetheart The Drunk", "duration": 335000, "link": "spotify:track:4iF3aJeZdi17XWYiFT3FFx"},
{"name": "Demon John", "artists": ["Jeff Buckley"], "album": "SKETCHES for My Sweetheart The Drunk", "duration": 311000, "link": "spotify:track:4cpT7hl8cMLk7dvsRofNXT"},
{"name": "Your Flesh Is So Nice", "artists": ["Jeff Buckley"], "album": "SKETCHES for My Sweetheart The Drunk", "duration": 215000, "link": "spotify:track:7h0RKOTCWNW335tKzu4OG7"},
{"name": "Jewel Box", "artists": ["Jeff Buckley"], "album": "SKETCHES for My Sweetheart The Drunk", "duration": 213000, "link": "spotify:track:5M3EGbv2NfDkNJ7tcARiCJ"},
{"name": "Satisfied Mind", "artists": ["Jeff Buckley"], "album": "SKETCHES for My Sweetheart The Drunk", "duration": 358000, "link": "spotify:track:4m1glKN9JCyV7VfTm1D28R"},
]}
