{"playlist_name": "SXSW 2012 Nathan All Days",
"http_link": "http://open.spotify.com/user/natelindydogg/playlist/5txPnW5XGm0qYquSlSQE6o",
"spotify_link": "spotify:user:natelindydogg:playlist:5txPnW5XGm0qYquSlSQE6o",
"songs": [
{"name": "Black Sheep", "artists": ["Metric"], "album": "Scott Pilgrim vs. the World (Original Motion Picture Soundtrack)", "duration": 296000, "link": "spotify:track:1CBQ8XGwcu7BcsT8iByvwE"},
{"name": "Combat Baby", "artists": ["Metric"], "album": "Old World Underground, Where Are You Now?", "duration": 210000, "link": "spotify:track:2KBgb53G7Yb0bt6IlY8JrI"},
{"name": "Dead Disco", "artists": ["Metric"], "album": "Old World Underground, Where Are You Now?", "duration": 206000, "link": "spotify:track:19CyChgF17xyVSkuRy5BGC"},
{"name": "Always A Friend", "artists": ["Alejandro Escovedo"], "album": "Real Animal", "duration": 216000, "link": "spotify:track:7136gj6H3nc3ZIKmJmxKRT"},
{"name": "That Old Black Hole", "artists": ["Dr. Dog"], "album": "Be The Void", "duration": 201000, "link": "spotify:track:27HUDvaWvjlrLhcsMDWgtd"},
{"name": "Nothing But Our Love", "artists": ["Dale Earnhardt Jr. Jr."], "album": "It's A Corporate World", "duration": 246000, "link": "spotify:track:1KQ1zcWbnHN9jIECk2wJQ4"},
{"name": "Morning Thought", "artists": ["Dale Earnhardt Jr. Jr."], "album": "It's A Corporate World", "duration": 215000, "link": "spotify:track:5EJ7vsK6xXOjQTQ1TxEum1"},
{"name": "Skeletons", "artists": ["Dale Earnhardt Jr. Jr."], "album": "It's A Corporate World", "duration": 139000, "link": "spotify:track:4FmXk2knLzKdGYB9I3Y1lV"},
{"name": "Simple Girl", "artists": ["Dale Earnhardt Jr. Jr."], "album": "It's A Corporate World", "duration": 143000, "link": "spotify:track:4VujpUd5p9qCSoF2F5ZFLo"},
{"name": "An Ugly Person On A Movie Screen", "artists": ["Dale Earnhardt Jr. Jr."], "album": "It's A Corporate World", "duration": 192000, "link": "spotify:track:7Mvn1GabwX7ork85UbfSBi"},
{"name": "God Only Knows", "artists": ["Dale Earnhardt Jr. Jr."], "album": "Horse Power EP", "duration": 194000, "link": "spotify:track:5j6N71LrZ6YV3DEtqUeLzK"},
{"name": "People C'mon", "artists": ["Delta Spirit"], "album": "Ode to Sunshine", "duration": 205000, "link": "spotify:track:1aY6BDvOrG1ph6HrDQPxo5"},
{"name": "California", "artists": ["Delta Spirit"], "album": "California", "duration": 220000, "link": "spotify:track:7AG7GaVRRRahY7NYzAkq57"},
{"name": "Trashcan", "artists": ["Delta Spirit"], "album": "Ode to Sunshine", "duration": 216000, "link": "spotify:track:4AZoPNYdHKWz5eeT3m5V6A"},
{"name": "Tomorrow Goes Away", "artists": ["Delta Spirit"], "album": "Ode to Sunshine", "duration": 90000, "link": "spotify:track:3zUE1KfsaIoIarrpzK4sxo"},
{"name": "Parade", "artists": ["Delta Spirit"], "album": "Ode to Sunshine", "duration": 185000, "link": "spotify:track:6TcJV62990rMnMQudYBdz4"},
{"name": "Jumper", "artists": ["Third Eye Blind"], "album": "Rhino Hi-Five: Third Eye Blind", "duration": 272000, "link": "spotify:track:6gkD0tbTaBy9t6meSK4aIL"},
{"name": "Semi-Charmed Life", "artists": ["Third Eye Blind"], "album": "Rhino Hi-Five: Third Eye Blind", "duration": 269000, "link": "spotify:track:6luSHkUXVmx3DKGN4TuRqF"},
{"name": "How's It Going To Be", "artists": ["Third Eye Blind"], "album": "Third Eye Blind", "duration": 253000, "link": "spotify:track:3Uvx1TO0Kg5HgGPk58lHXv"},
{"name": "Never Let You Go", "artists": ["Third Eye Blind"], "album": "Rhino Hi-Five: Third Eye Blind", "duration": 237000, "link": "spotify:track:7mP4fGwTDxoTOfQtxeAiJS"},
{"name": "Graduate", "artists": ["Third Eye Blind"], "album": "Third Eye Blind", "duration": 188000, "link": "spotify:track:6pLko0BJo4OmvbmPbLURsl"},
{"name": "Rooks", "artists": ["Shearwater"], "album": "Rook", "duration": 201000, "link": "spotify:track:3wS568uaBrv1ULtMmh9bbN"},
{"name": "Meridian", "artists": ["Shearwater"], "album": "The Golden Archipelago", "duration": 217000, "link": "spotify:track:65KRGiFrKByP3tBDygiNh4"},
{"name": "Black Eyes", "artists": ["Shearwater"], "album": "The Golden Archipelago", "duration": 220000, "link": "spotify:track:3AE9azPMzbGn5jWljH2trX"},
{"name": "The Snow Leopard", "artists": ["Shearwater"], "album": "Rook", "duration": 308000, "link": "spotify:track:3SHPTPPnB3M2e4ZdHq0gOd"},
{"name": "Landscape At Speed", "artists": ["Shearwater"], "album": "The Golden Archipelago", "duration": 273000, "link": "spotify:track:11v3XYKDpuzQmhLjFS5m6P"},
{"name": "King Of The Party", "artists": ["Big Sam's Funky Nation"], "album": "King Of The Party", "duration": 212000, "link": "spotify:track:6zhkRlrWa9eNe5zpZbqGQ7"},
{"name": "Krunked Up", "artists": ["Big Sam's Funky Nation"], "album": "King Of The Party", "duration": 285000, "link": "spotify:track:5ServfdXax96gJb9c48cFk"},
{"name": "Hard To Handle", "artists": ["Big Sam's Funky Nation"], "album": "King Of The Party", "duration": 253000, "link": "spotify:track:2fAHplwEI9uuTSPaG20d3j"},
{"name": "Big Ole Booty", "artists": ["Big Sam's Funky Nation"], "album": "King Of The Party", "duration": 227000, "link": "spotify:track:4dDZf9N8jtjxGMWgu2KMyg"},
{"name": "Rage On!", "artists": ["Big Sam's Funky Nation"], "album": "King Of The Party", "duration": 164000, "link": "spotify:track:14nBOVonNV00uftfB3vgZY"},
{"name": "Club Foot", "artists": ["Kasabian"], "album": "Kasabian", "duration": 215000, "link": "spotify:track:09upEACyRhfvWbrTlExjWG"},
{"name": "Reason Is Treason", "artists": ["Kasabian"], "album": "Kasabian", "duration": 275000, "link": "spotify:track:5EtPPOjUNAN67tAo5pkbdl"},
{"name": "L.S.F.", "artists": ["Kasabian"], "album": "Kasabian", "duration": 197000, "link": "spotify:track:3SUi6ssCYuyrOWal9csHNC"},
{"name": "Animal", "artists": ["Miike Snow"], "album": "Miike Snow", "duration": 263000, "link": "spotify:track:1uxdxSC2bfUFYVqxvejVC3"},
{"name": "Burial", "artists": ["Miike Snow"], "album": "Miike Snow", "duration": 261000, "link": "spotify:track:3hAISHuncayUMztDDvkwmS"},
{"name": "Song for No One", "artists": ["Miike Snow"], "album": "Miike Snow", "duration": 249000, "link": "spotify:track:15JHH5FBawCL7DmCcUxlUp"},
{"name": "Silvia", "artists": ["Miike Snow"], "album": "Miike Snow", "duration": 386000, "link": "spotify:track:2Cq2BrkoxqMvP3hcJHWNga"},
{"name": "Black & Blue", "artists": ["Miike Snow"], "album": "Miike Snow", "duration": 220000, "link": "spotify:track:2cOCunrzyHVpTrTwSIKRbt"},
{"name": "A Horse Is Not A Home", "artists": ["Miike Snow"], "album": "Miike Snow", "duration": 253000, "link": "spotify:track:3BpFOojrFz0ZUwDVuaFU64"},
{"name": "Plastic Jungle", "artists": ["Miike Snow"], "album": "Miike Snow", "duration": 234000, "link": "spotify:track:2LPUelHdNmjakaSZks8C8z"},
{"name": "Why Even Try - feat. Sara Quin", "artists": ["Theophilus London", "Sara Quin"], "album": "Lovers Holiday", "duration": 255000, "link": "spotify:track:2rrPQMdDbRZyMtQooLaIKO"},
{"name": "Say Goodnight To The World", "artists": ["Dax Riggs"], "album": "Say Goodnight To The World", "duration": 259000, "link": "spotify:track:0U4z1cLmR29F3q3V1KKv6L"},
{"name": "Didn't Know Yet What I'd Know When I Was Bleedin'", "artists": ["Dax Riggs"], "album": "We Sing Of Only Blood Or Love", "duration": 159000, "link": "spotify:track:0b2vLXSnPYkL2EjS2Jk5Ao"},
{"name": "I Hear Satan", "artists": ["Dax Riggs"], "album": "Say Goodnight To The World", "duration": 180000, "link": "spotify:track:1kK0nGKNYAP9Eskbsoi8hD"},
{"name": "You Were Born To Be My Gallows", "artists": ["Dax Riggs"], "album": "Say Goodnight To The World", "duration": 174000, "link": "spotify:track:0KKLrAomyGYwKWNBFOVKiI"},
{"name": "Let Me Be Your Cigarette", "artists": ["Dax Riggs"], "album": "Say Goodnight To The World", "duration": 168000, "link": "spotify:track:7ttQyrFBg14B5jtXO2DSlQ"},
{"name": "Don't Stop", "artists": ["Electric Touch"], "album": "Don't Stop - EP", "duration": 191000, "link": "spotify:track:7LXG1iW3Pnftpx4czjN8kG"},
{"name": "Love In Our Hearts", "artists": ["Electric Touch"], "album": "Electric Touch", "duration": 160000, "link": "spotify:track:4pvjpuE8DYa7HQjtupxt1Y"},
{"name": "Magnetic", "artists": ["Electric Touch"], "album": "Don't Stop - EP", "duration": 228000, "link": "spotify:track:5mjNf5zB3lw8BICGHtc1it"},
{"name": "Dominos", "artists": ["Electric Touch"], "album": "Don't Stop - EP", "duration": 212000, "link": "spotify:track:7FqnMMpsuWaFdYkFMB3W6b"},
{"name": "Call My Name", "artists": ["Electric Touch"], "album": "Electric Touch", "duration": 222000, "link": "spotify:track:1Dr1lOQGUTZ0yRwq7nQmRb"},
{"name": "Animal", "artists": ["Neon Trees"], "album": "Habits", "duration": 212000, "link": "spotify:track:1fBl642IhJOE5U319Gy2Go"},
{"name": "Everybody Talks", "artists": ["Neon Trees"], "album": "Everybody Talks", "duration": 179000, "link": "spotify:track:5JGxJFdgOQdJZdmyEzDtTj"},
{"name": "1983", "artists": ["Neon Trees"], "album": "Habits", "duration": 223000, "link": "spotify:track:4DJLcyfnyEGlUejAEAX4az"},
{"name": "Your Surrender", "artists": ["Neon Trees"], "album": "Habits", "duration": 221000, "link": "spotify:track:17QodENDMk3o1nPgPqfs3Y"},
{"name": "Sins Of My Youth", "artists": ["Neon Trees"], "album": "Habits", "duration": 219000, "link": "spotify:track:6Tg1j7uoHfAl16bbPNC8Gc"},
{"name": "How'm I Gonna Get Back Home", "artists": ["He's My Brother She's My Sister"], "album": "He's My Brother She's My Sister EP", "duration": 218000, "link": "spotify:track:0EsNP48ZxnuQx303EcckwI"},
{"name": "Time Spent in Los Angeles", "artists": ["Dawes"], "album": "Nothing Is Wrong", "duration": 268000, "link": "spotify:track:7AFtKtn2WnFdKvmH90dEBT"},
{"name": "When My Time Comes (Single Version)", "artists": ["Dawes"], "album": "When My Time Comes - Single", "duration": 300000, "link": "spotify:track:6tgZF7c1n3yhtEChf70Ilm"},
{"name": "If I Wanted Someone", "artists": ["Dawes"], "album": "Nothing Is Wrong", "duration": 279000, "link": "spotify:track:3AEBanY12LrfnintiDqZ3f"},
{"name": "Million Dollar Bill", "artists": ["Dawes"], "album": "Nothing Is Wrong", "duration": 253000, "link": "spotify:track:3GhzsdLDxVt6bZ3u2Nsz2z"},
{"name": "A Little Bit of Everything", "artists": ["Dawes"], "album": "Nothing Is Wrong", "duration": 339000, "link": "spotify:track:6M2UVLUMGZiwwkKgtDcHUR"},
{"name": "Love Me", "artists": ["The Little Willies "], "album": "...Featuring", "duration": 233000, "link": "spotify:track:7spsaHi2B8nDEaJbjiTmoZ"},
{"name": "Hold On", "artists": ["Alabama Shakes"], "album": "Hold On", "duration": 229000, "link": "spotify:track:7c13Xlndg43PnSzpHRD11d"},
{"name": "Nerve Jamming", "artists": ["Bass Drum Of Death"], "album": "GB City", "duration": 157000, "link": "spotify:track:3kRURM3BXkcSEGX7NrwXyG"},
{"name": "GB City", "artists": ["Bass Drum Of Death"], "album": "GB City", "duration": 184000, "link": "spotify:track:22itI3VLvROXkQFIIq6WPX"},
{"name": "Get Found", "artists": ["Bass Drum Of Death"], "album": "GB City", "duration": 181000, "link": "spotify:track:4ZwPUKS2nsfJ6AhtWVGUuZ"},
{"name": "Velvet Itch", "artists": ["Bass Drum Of Death"], "album": "GB City", "duration": 177000, "link": "spotify:track:6eyBwN0SoUhCP6qglQGECR"},
{"name": "Heart Attack Kid", "artists": ["Bass Drum Of Death"], "album": "GB City", "duration": 163000, "link": "spotify:track:47k9FUgMyvaDcIJn1wvXOo"},
{"name": "Stop", "artists": ["The Chain Gang Of 1974"], "album": "Wayward Fire", "duration": 245000, "link": "spotify:track:1XAHeyENie2o6zCYilwewy"},
{"name": "Devil Is A Lady", "artists": ["The Chain Gang Of 1974"], "album": "Wayward Fire", "duration": 350000, "link": "spotify:track:3EF0cGT7WZq7UNjsxRJ5vF"},
{"name": "Hold On", "artists": ["The Chain Gang Of 1974"], "album": "Wayward Fire", "duration": 489000, "link": "spotify:track:2cSNluLIxaASPTTsmqv0Xa"},
{"name": "Taste of Heaven", "artists": ["The Chain Gang Of 1974"], "album": "Wayward Fire", "duration": 315000, "link": "spotify:track:50oEBiNYR4xdeUZJGd1P2I"},
{"name": "Matter Of Time", "artists": ["The Chain Gang Of 1974"], "album": "Wayward Fire", "duration": 318000, "link": "spotify:track:7p7snmzI1tcDfHw914jjvl"},
{"name": "Let's Go Surfing", "artists": ["The Drums"], "album": "The Drums", "duration": 174000, "link": "spotify:track:49skdn8Truaufvcz8BXmtT"},
{"name": "Down By The Water", "artists": ["The Drums"], "album": "The Drums", "duration": 206000, "link": "spotify:track:6NFgv7jhNpbmiQhZqodx0w"},
{"name": "Book of Revelation", "artists": ["The Drums"], "album": "Portamento", "duration": 210000, "link": "spotify:track:34xKCCufqJSuEjqXJ0RzRY"},
{"name": "Days", "artists": ["The Drums"], "album": "Portamento", "duration": 269000, "link": "spotify:track:6113aOfHIC0vbZVDZ6PpRV"},
{"name": "Money", "artists": ["The Drums"], "album": "Portamento (Commentary Version)", "duration": 234000, "link": "spotify:track:6jG0ltS4ia3MTQ5EGMXQCj"},
{"name": "I Like It", "artists": ["Foxy Shazam"], "album": "The Church of Rock and Roll", "duration": 168000, "link": "spotify:track:5ZSgw6radpqZRIpbc8vkS2"},
{"name": "Wanna-be Angel", "artists": ["Foxy Shazam"], "album": "Foxy Shazam", "duration": 202000, "link": "spotify:track:3pugh523wdgbWbNV0iR5HG"},
{"name": "Unstoppable", "artists": ["Foxy Shazam"], "album": "Foxy Shazam", "duration": 214000, "link": "spotify:track:7inqk2aOungrJvYeBh2FQ8"},
{"name": "Oh Lord", "artists": ["Foxy Shazam"], "album": "Foxy Shazam", "duration": 251000, "link": "spotify:track:5iJU96441eAZ2VdWgxdyJa"},
{"name": "Be Calm", "artists": ["Fun."], "album": "Aim and Ignite [Deluxe Version]", "duration": 250000, "link": "spotify:track:0SHPEXmOSJL4Og3aJluoKd"},
{"name": "All The Pretty Girls", "artists": ["Fun."], "album": "Aim and Ignite [Deluxe Version]", "duration": 203000, "link": "spotify:track:1TQyRzRnGJflBhUHAwtk1x"},
{"name": "At Least I'm Not As Sad", "artists": ["Fun."], "album": "Aim and Ignite [Deluxe Version]", "duration": 247000, "link": "spotify:track:3I7bOKGX8oxIQHFThQxtH4"},
{"name": "Light A Roman Candle With Me", "artists": ["Fun."], "album": "Aim and Ignite [Deluxe Version]", "duration": 185000, "link": "spotify:track:5pxGxR8ltHAluRyn9FSKOh"},
{"name": "We Are Young - feat. Janelle Monáe", "artists": ["Fun."], "album": "We Are Young", "duration": 251000, "link": "spotify:track:3ehrxAhYms24KLPG8FZe0W"},
{"name": "Oh, Mary Don't You Weep", "artists": ["Mike Farris"], "album": "Salvation In Lights", "duration": 285000, "link": "spotify:track:44PcmUyPsgL7iqnbLDxTIL"},
{"name": "Enemy Among Us", "artists": ["Paper Route"], "album": "Absence", "duration": 285000, "link": "spotify:track:0i81qbeTGar1t7Mp7zNyar"},
{"name": "Wish", "artists": ["Paper Route"], "album": "Absence", "duration": 231000, "link": "spotify:track:2Yt70dp62QrnAMpedeqYaS"},
{"name": "Carousel", "artists": ["Paper Route"], "album": "Absence", "duration": 211000, "link": "spotify:track:5C1d7ROKhZQdGwjR8oQX6I"},
{"name": "Dance On Our Graves", "artists": ["Paper Route"], "album": "Absence", "duration": 357000, "link": "spotify:track:7LNj7NAqnPo3C8Qprvtc72"},
{"name": "Better Life", "artists": ["Paper Route"], "album": "Better Life", "duration": 286000, "link": "spotify:track:6q28OBHejDGZz48QIaXLBF"},
{"name": "Life Design", "artists": ["The Parlotones"], "album": "Life Design", "duration": 207000, "link": "spotify:track:14ZySfWOMEMoUnp8OVGDYM"},
{"name": "We Call This Dancing (Single Edit)", "artists": ["The Parlotones"], "album": "We Call This Dancing (Single Edit)", "duration": 235000, "link": "spotify:track:45GUBgLiEtv6QirToVqWzn"},
{"name": "A More Perfect Union", "artists": ["Titus Andronicus"], "album": "The Monitor", "duration": 429000, "link": "spotify:track:515qE0YyUWivEobvHGpN7o"},
{"name": "Titus Andronicus Forever", "artists": ["Titus Andronicus"], "album": "The Monitor", "duration": 115000, "link": "spotify:track:4KK2RftZcEydipbeZApQwO"},
{"name": "Light Of The Morning", "artists": ["Band Of Skulls"], "album": "Baby Darling Doll Face Honey", "duration": 164000, "link": "spotify:track:5IPvlTwK5puCgihZyPRlbI"},
{"name": "Death By Diamonds And Pearls", "artists": ["Band Of Skulls"], "album": "Baby Darling Doll Face Honey", "duration": 193000, "link": "spotify:track:3wRMqYxKiNxjTFGDDn55rI"},
{"name": "I Know What I Am", "artists": ["Band Of Skulls"], "album": "Baby Darling Doll Face Honey", "duration": 198000, "link": "spotify:track:5VBHqTrMzUez5ZtktQQUcu"},
{"name": "Sweet Sour", "artists": ["Band Of Skulls"], "album": "Sweet Sour", "duration": 202000, "link": "spotify:track:6zp3uICwH4sIjgoYbR0S1G"},
{"name": "Friends - Soundtrack Album Version", "artists": ["Band Of Skulls"], "album": "The Twilight Saga: New Moon Original Motion Picture Soundtrack", "duration": 190000, "link": "spotify:track:1Oiawgs3gXm8NI6gLqKszk"},
{"name": "Beast In Peace", "artists": ["Bear In Heaven"], "album": "Beast Rest Forth Mouth", "duration": 257000, "link": "spotify:track:47XuWZlCUtHzo9BaGFsdQd"},
{"name": "Wholehearted Mess", "artists": ["Bear In Heaven"], "album": "Beast Rest Forth Mouth", "duration": 182000, "link": "spotify:track:23dKO2USIZXts7InaFQBCZ"},
{"name": "You Do You", "artists": ["Bear In Heaven"], "album": "Beast Rest Forth Mouth", "duration": 224000, "link": "spotify:track:5T7Czvic5aHHQUX7CyQ1qT"},
{"name": "Lovesick Teenagers", "artists": ["Bear In Heaven"], "album": "Beast Rest Forth Mouth", "duration": 196000, "link": "spotify:track:70IMZGJrOyqY2rLlDQvrb6"},
{"name": "Ultimate Satisfaction", "artists": ["Bear In Heaven"], "album": "Beast Rest Forth Mouth", "duration": 266000, "link": "spotify:track:71kyKU3jTc0PQ45ybkY4kx"},
{"name": "Tiny Spark", "artists": ["Brendan Benson"], "album": "Lapalco", "duration": 194000, "link": "spotify:track:7o5H7I6HX9qVrJH6DhvP6R"},
{"name": "Metarie", "artists": ["Brendan Benson"], "album": "Lapalco", "duration": 207000, "link": "spotify:track:1rQy03wiTUFkbXi5nTOIob"},
{"name": "Folk Singer", "artists": ["Brendan Benson"], "album": "Lapalco", "duration": 229000, "link": "spotify:track:1X21oxbHL1drj71Cf1gCXZ"},
{"name": "Tea", "artists": ["Brendan Benson"], "album": "One Mississippi", "duration": 68000, "link": "spotify:track:1CYaT7au49HLuPuNErJjiz"},
{"name": "Sittin' Pretty", "artists": ["Brendan Benson"], "album": "One Mississippi", "duration": 174000, "link": "spotify:track:6otu0L60xyz9zws2bI3D1u"},
{"name": "Dancing In The Dark", "artists": ["Bruce Springsteen"], "album": "Greatest Hits", "duration": 243000, "link": "spotify:track:0mHhAIdFdsvDCG9azUvIdb"},
{"name": "We Take Care Of Our Own", "artists": ["Bruce Springsteen"], "album": "We Take Care Of Our Own", "duration": 234000, "link": "spotify:track:7MybLKu8ni9uOaWmSTCoDk"},
{"name": "Trapped - Live", "artists": ["Bruce Springsteen & The E Street Band"], "album": "The Essential Bruce Springsteen", "duration": 308000, "link": "spotify:track:76Z29Zv9VmD6Rgu1ri7UKe"},
{"name": "Sidewalk Safari", "artists": ["Chairlift"], "album": "Something", "duration": 229000, "link": "spotify:track:6nsZ23hRFXCVkk9NwuzAz0"},
{"name": "Wrong Opinion", "artists": ["Chairlift"], "album": "Something", "duration": 303000, "link": "spotify:track:6fAQ5boPt3dPojWBVpaWE1"},
{"name": "I Belong In Your Arms", "artists": ["Chairlift"], "album": "Something", "duration": 207000, "link": "spotify:track:0aqRkWPAL9BGCvvdSiXaE9"},
{"name": "Hot As Hell - Original", "artists": ["Drop The Lime"], "album": "Hot As Hell", "duration": 188000, "link": "spotify:track:1XmypxM1Ow4jpJj7dIt8Fa"},
{"name": "Sex Sax", "artists": ["Drop The Lime"], "album": "Sex Sax", "duration": 284000, "link": "spotify:track:0IwYIsVEQNyb63n4tjvYul"},
{"name": "Shake Baby Shake", "artists": ["Drop The Lime"], "album": "Shake Baby Shake", "duration": 156000, "link": "spotify:track:6kCbMEfJ2Kemqy6VgZhdnU"},
{"name": "Deconstruction", "artists": ["Fanfarlo"], "album": "Deconstruction", "duration": 293000, "link": "spotify:track:2uPX16G1iZdmHDOyRfEp93"},
{"name": "I'm A Pilot", "artists": ["Fanfarlo"], "album": "Reservoir", "duration": 271000, "link": "spotify:track:50slRMlaHzX4aYPxZ5PzNn"},
{"name": "Ghosts", "artists": ["Fanfarlo"], "album": "Reservoir", "duration": 258000, "link": "spotify:track:7LeV1XTdSEsQPOsAieSpXP"},
{"name": "The Walls Are Coming Down", "artists": ["Fanfarlo"], "album": "Reservoir", "duration": 255000, "link": "spotify:track:1xXLNhxX57cZqLsDPlKZpc"},
{"name": "Shiny Things", "artists": ["Fanfarlo"], "album": "Shiny Things", "duration": 273000, "link": "spotify:track:1JHn7AVvISP1YrMQSa4co2"},
{"name": "Criminal", "artists": ["Fiona Apple"], "album": "Tidal", "duration": 342000, "link": "spotify:track:4MHB6aVYOgd3j4qtRPTbsh"},
{"name": "Head On", "artists": ["The Jesus And Mary Chain"], "album": "Automatic", "duration": 251000, "link": "spotify:track:0XK3azZuLvHjHG3aHDAfHB"},
{"name": "Darklands", "artists": ["The Jesus And Mary Chain"], "album": "Darklands", "duration": 329000, "link": "spotify:track:604NVJumUJY9kGlFKTu2ei"},
{"name": "Happy When It Rains", "artists": ["The Jesus And Mary Chain"], "album": "Darklands", "duration": 217000, "link": "spotify:track:3N46STykuPaGLw2lHl3e3R"},
{"name": "Just Like Honey", "artists": ["The Jesus And Mary Chain"], "album": "Rhino Hi-Five: Jesus And Mary Chain", "duration": 182000, "link": "spotify:track:0tqPdq1PtwqtabuerWvv85"},
{"name": "Sometimes Always", "artists": ["The Jesus And Mary Chain"], "album": "Stoned And Dethroned", "duration": 152000, "link": "spotify:track:11sxpJrfYJFxkA77PauDj4"},
{"name": "I Predict a Riot", "artists": ["Kaiser Chiefs"], "album": "The Coolest Songs in the World! Vol. 7", "duration": 232000, "link": "spotify:track:4nBAFFXX2NPDuT4gxQSWmh"},
{"name": "Everyday I Love You Less and Less", "artists": ["Kaiser Chiefs"], "album": "Employment", "duration": 218000, "link": "spotify:track:0obv9ng3ulbtAFFBiYrxJe"},
{"name": "Modern Way", "artists": ["Kaiser Chiefs"], "album": "Employment (Ecopac)", "duration": 244000, "link": "spotify:track:037MX2T2yMS0aZKWkhcAv6"},
{"name": "Na Na Na Na Naa", "artists": ["Kaiser Chiefs"], "album": "Employment (Ecopac)", "duration": 180000, "link": "spotify:track:28H1omMTTE98ZbhEqLt2ck"},
{"name": "Oh My God", "artists": ["Kaiser Chiefs"], "album": "Employment (Ecopac)", "duration": 215000, "link": "spotify:track:6PSSJYFUemqRYp1r7nc9T9"},
{"name": "Never Miss A Beat", "artists": ["Kaiser Chiefs"], "album": "Off With Their Heads", "duration": 187000, "link": "spotify:track:1CSYUa50rrQy7UYn1z7hNB"},
{"name": "Ruby", "artists": ["Kaiser Chiefs"], "album": "Yours Truly, Angry Mob", "duration": 204000, "link": "spotify:track:2fAIfPLrPUTW1AmJRR428Q"},
{"name": "The Angry Mob", "artists": ["Kaiser Chiefs"], "album": "Yours Truly, Angry Mob", "duration": 287000, "link": "spotify:track:0Zxwj1KVH3xhqtaFP741KG"},
{"name": "Somewhere Only We Know", "artists": ["Keane"], "album": "Hopes and Fears", "duration": 238000, "link": "spotify:track:5LOaKdW9D2Gl9neAN94NbR"},
{"name": "Bend & Break", "artists": ["Keane"], "album": "Hopes And Fears", "duration": 218000, "link": "spotify:track:04YMjPTBvHj65k9dJMC4BZ"},
{"name": "We Might As Well Be Strangers", "artists": ["Keane"], "album": "Hopes And Fears", "duration": 191000, "link": "spotify:track:1dLl91qCvpTlBvaqAQIE9U"},
{"name": "Atlantic", "artists": ["Keane"], "album": "Under The Iron Sea", "duration": 254000, "link": "spotify:track:3LdKufJAbl8faACLyn73dI"},
{"name": "Is It Any Wonder?", "artists": ["Keane"], "album": "Under The Iron Sea", "duration": 186000, "link": "spotify:track:3RyuWd7xlLJdLddH6Kt2o6"},
{"name": "Nothing In My Way", "artists": ["Keane"], "album": "Under The Iron Sea", "duration": 240000, "link": "spotify:track:6rv1dEQww8zRwUwR0DphmO"},
{"name": "Haunted Heart", "artists": ["little hurricane"], "album": "Bands Under the Radar, Vol. 5: Rock N Roll", "duration": 165000, "link": "spotify:track:4iPeFC6D34SwhrXe9VEOz5"},
{"name": "I Worship You", "artists": ["The Little Willies "], "album": "For The Good Times", "duration": 171000, "link": "spotify:track:1GjLFQkYFw4nDLioILNFKo"},
{"name": "Remember Me", "artists": ["The Little Willies "], "album": "For The Good Times", "duration": 239000, "link": "spotify:track:4F2o2Er3SgQyVZvsjrygcs"},
{"name": "Diesel Smoke, Dangerous Curves", "artists": ["The Little Willies "], "album": "For The Good Times", "duration": 185000, "link": "spotify:track:5rj5BagtEwqj6R05kVJY1F"},
{"name": "Jolene", "artists": ["The Little Willies "], "album": "For The Good Times", "duration": 291000, "link": "spotify:track:7a80VS1OnPl0QsQf4DkXs9"},
{"name": "Amongster", "artists": ["POLIÇA"], "album": "Give You The Ghost", "duration": 240000, "link": "spotify:track:02NecTSDJSDFEmz35mwfRZ"},
{"name": "I See My Mother", "artists": ["POLIÇA"], "album": "Give You The Ghost", "duration": 266000, "link": "spotify:track:0ncUpqx7Vlz6Lbeye6Ozp7"},
{"name": "Dark Star", "artists": ["POLIÇA"], "album": "Give You The Ghost", "duration": 302000, "link": "spotify:track:2DXRZYlPkP4Bnk8FfZqBkj"},
{"name": "Lay Your Cards Out", "artists": ["POLIÇA", "Mike Noyce"], "album": "Give You The Ghost", "duration": 244000, "link": "spotify:track:2NbSzyMiK2oZov8r5Yddcf"},
{"name": "Wandering Star", "artists": ["POLIÇA", "Mike Noyce"], "album": "Give You The Ghost", "duration": 304000, "link": "spotify:track:5f3eGJLHFZcu3o5XyrrJNS"},
{"name": "Blastoff", "artists": ["Reptar"], "album": "Oblangle Fizz Y'all", "duration": 229000, "link": "spotify:track:72JYS69F8CPUYuOtxu1VWW"},
{"name": "Stuck In My Id", "artists": ["Reptar"], "album": "Oblangle Fizz Y'all", "duration": 313000, "link": "spotify:track:3baRabbEPY4GOEpXxweAGj"},
{"name": "Love More", "artists": ["Sharon Van Etten"], "album": "Epic", "duration": 314000, "link": "spotify:track:6SHfaJ1GWWSbMNc7ekQgHp"},
{"name": "Serpents", "artists": ["Sharon Van Etten"], "album": "Tramp", "duration": 184000, "link": "spotify:track:0GPd750u05eqe5GXfpBSVz"},
{"name": "Simple Song", "artists": ["The Shins"], "album": "Simple Song", "duration": 256000, "link": "spotify:track:5EoKQDGE2zxrTfRFZF52u5"},
{"name": "Phantom Limb", "artists": ["The Shins"], "album": "Wincing The Night Away", "duration": 288000, "link": "spotify:track:4l8knlwTeoTmSnGi45kqZ8"},
{"name": "Can't Believe A Single Word", "artists": ["VHS or Beta"], "album": "Bring On The Comets", "duration": 223000, "link": "spotify:track:7G2uAjfOeFHsECCYaFfzM6"},
{"name": "Breaking Bones", "artists": ["VHS or Beta"], "album": "DIAMONDS AND DEATH", "duration": 262000, "link": "spotify:track:7q1QK3jqrjBDQA5Qi49Okz"},
{"name": "I Found A Reason", "artists": ["VHS or Beta"], "album": "DIAMONDS AND DEATH", "duration": 352000, "link": "spotify:track:1wgjERVFDszqXywQ9EuFT2"},
{"name": "Night On Fire", "artists": ["VHS or Beta"], "album": "Night On Fire", "duration": 242000, "link": "spotify:track:0er8WROBNuNonxt6YvsVp3"},
{"name": "Guns of Brixton", "artists": ["Jimmy Cliff"], "album": "Sacred Fire", "duration": 219000, "link": "spotify:track:0YGUgowu18FBjHiuOAWBKL"},
{"name": "Many Rivers To Cross", "artists": ["Jimmy Cliff"], "album": "Many Rivers to Cross", "duration": 161000, "link": "spotify:track:2jQQJgvmr8fmTsWULa2pct"},
{"name": "Heartbreak Warfare", "artists": ["John Mayer"], "album": "Battle Studies", "duration": 270000, "link": "spotify:track:4gs07VlJST4bdxGbBsXVue"},
{"name": "The Book Of Love", "artists": ["The Magnetic Fields"], "album": "69 Love Songs", "duration": 162000, "link": "spotify:track:6UGpcXcENaUqQKPc6oqOe4"},
{"name": "California Girls", "artists": ["The Magnetic Fields"], "album": "Distortion", "duration": 180000, "link": "spotify:track:1id8C2LdzAayYwyWqfBCrk"},
{"name": "You Must Be Out of Your Mind", "artists": ["The Magnetic Fields"], "album": "Realism", "duration": 192000, "link": "spotify:track:2ly4nED24dIDLq4RWxHMFC"},
{"name": "I Don't Want To Get Over You", "artists": ["The Magnetic Fields"], "album": "69 Love Songs", "duration": 142000, "link": "spotify:track:09YfILH3QY7POQbhBc7DNv"},
{"name": "Bright Lights", "artists": ["Gary Clark Jr."], "album": "Gary Clark Jr.", "duration": 312000, "link": "spotify:track:5YVxDOpo3E7uyZbQDIPb2O"},
{"name": "Don't Owe You a Thang", "artists": ["Gary Clark Jr."], "album": "Gary Clark Jr.", "duration": 214000, "link": "spotify:track:6kHWGVOuGXaIJRB4lX7OZ8"},
{"name": "The Life", "artists": ["Gary Clark Jr."], "album": "Gary Clark Jr.", "duration": 278000, "link": "spotify:track:0f4CbfVC63rIPkEWbhlt9N"},
{"name": "Mister Cellophane", "artists": ["John C. Reilly"], "album": "Chicago - Music From The Miramax Motion Picture", "duration": 238000, "link": "spotify:track:6TtN9cU9bK6TJX0DBSu6pd"},
{"name": "Walk Hard", "artists": ["John C. Reilly"], "album": "Walk Hard: The Dewey Cox Story "Original Motion Picture Soundtrack"", "duration": 167000, "link": "spotify:track:1ti7FlOjQV7ZmgMjN1M4Oc"},
{"name": "Furr", "artists": ["Blitzen Trapper"], "album": "Furr", "duration": 248000, "link": "spotify:track:6n1zT8W5EaIYvWIT2DyROL"},
{"name": "Black River Killer", "artists": ["Blitzen Trapper"], "album": "Furr", "duration": 208000, "link": "spotify:track:6tbkCukDV2wEiyg42ZJJbC"},
{"name": "God & Suicide", "artists": ["Blitzen Trapper"], "album": "Furr", "duration": 141000, "link": "spotify:track:2fuyuslU3y01zd8GNRFbO4"},
{"name": "Destroyer of the Void", "artists": ["Blitzen Trapper"], "album": "Destroyer of the Void", "duration": 377000, "link": "spotify:track:1ZGpzEji3pChx6M3zD8XDq"},
{"name": "Laughing Lover", "artists": ["Blitzen Trapper"], "album": "Destroyer of the Void", "duration": 190000, "link": "spotify:track:0fUwQi4CdMcvSMXskXPSvn"},
{"name": "Mr. Jones", "artists": ["Counting Crows"], "album": "Films About Ghosts (The Best Of Counting Crows)", "duration": 273000, "link": "spotify:track:5kfz5F8TfsFs05MBMqkcOz"},
{"name": "Round Here", "artists": ["Counting Crows"], "album": "Films About Ghosts (The Best Of Counting Crows)", "duration": 331000, "link": "spotify:track:4KeNKOPLRnUoW8rjIA9gd3"},
{"name": "A Long December", "artists": ["Counting Crows"], "album": "Films About Ghosts (The Best Of Counting Crows)", "duration": 297000, "link": "spotify:track:4t9lT9WMlCsQRXkx8dyX2y"},
{"name": "She Blinded Me With Science", "artists": ["Thomas Dolby"], "album": "Retrospectacle - The Best Of Thomas Dolby", "duration": 221000, "link": "spotify:track:0BWravaqj9rKdOU8RWXhuf"},
{"name": "Nothing New Under The Sun", "artists": ["Thomas Dolby"], "album": "A Map Of The Floating City", "duration": 274000, "link": "spotify:track:3Y4xFKNBDNAbYR5oahctVT"},
{"name": "17 Hills (feat. Mark Knopfler, Natalie MacMaster)", "artists": ["Thomas Dolby"], "album": "A Map Of The Floating City", "duration": 461000, "link": "spotify:track:5YLhoIgtfWcR6sFAkgAgEi"},
{"name": "Hyperactive!", "artists": ["Thomas Dolby"], "album": "Retrospectacle - The Best Of Thomas Dolby", "duration": 253000, "link": "spotify:track:4saaODYMt6sFe5ErHGX7rk"},
{"name": "Close But No Cigar", "artists": ["Thomas Dolby"], "album": "Retrospectacle - The Best Of Thomas Dolby", "duration": 267000, "link": "spotify:track:73NPD5V6RNID5QoVKIYPDE"},
{"name": "I Love You Goodbye", "artists": ["Thomas Dolby"], "album": "Retrospectacle - The Best Of Thomas Dolby", "duration": 358000, "link": "spotify:track:6Vnrw2y15WnSlJP2bML115"},
{"name": "Airhead", "artists": ["Thomas Dolby"], "album": "Alien's Ate My Buick", "duration": 309000, "link": "spotify:track:23Z1zCRT68TKZdqqCs9qod"},
{"name": "The Ability To Swing", "artists": ["Thomas Dolby"], "album": "Alien's Ate My Buick", "duration": 269000, "link": "spotify:track:44dZOmNEDLYKYJtG7zlwJ1"},
{"name": "Dominos", "artists": ["The Big Pink"], "album": "A Brief History Of Love", "duration": 226000, "link": "spotify:track:0IHUvHnlyAFTbnc4W1FmPT"},
{"name": "Hit The Ground (Superman)", "artists": ["The Big Pink"], "album": "Future This", "duration": 296000, "link": "spotify:track:6KCU2PmHHDFbSMVfPlRB5y"},
{"name": "Stay Gold", "artists": ["The Big Pink"], "album": "Future This", "duration": 218000, "link": "spotify:track:5mly3hWIPCbCl305awiWcm"},
{"name": "Give It Up", "artists": ["The Big Pink"], "album": "Future This", "duration": 289000, "link": "spotify:track:4hwvNfsw7Y7WOh236GOR3P"},
{"name": "Future This", "artists": ["The Big Pink"], "album": "Future This", "duration": 236000, "link": "spotify:track:0lJv0Ei2lmcOL65T0VFAOw"},
{"name": "Pali Gap / Hey Baby (New Rising Sun)", "artists": ["Lukas Nelson and Promise of the Real"], "album": "Promise of the Real", "duration": 319000, "link": "spotify:track:0JT0D83NTt3o2VbZSI3f5K"},
{"name": "Four Letter Word", "artists": ["Lukas Nelson and Promise of the Real"], "album": "Promise of the Real", "duration": 242000, "link": "spotify:track:6f2BzDHgFiHYQiy5d4TvsC"},
{"name": "Don’t Lose Your Mind", "artists": ["Lukas Nelson and Promise of the Real"], "album": "Promise of the Real", "duration": 298000, "link": "spotify:track:35jorcwHvbnNR99zLdXovm"},
{"name": "She Sells Sanctuary", "artists": ["The Cult"], "album": "Pure Cult", "duration": 252000, "link": "spotify:track:66glXjjFvlS5r1gDUK4ugq"},
{"name": "Fire Woman", "artists": ["The Cult"], "album": "Pure Cult", "duration": 307000, "link": "spotify:track:1Twr9ElGR91uhIiJtiLyVI"},
{"name": "Lil’ Devil", "artists": ["The Cult"], "album": "Pure Cult", "duration": 166000, "link": "spotify:track:3Btwfnel16SajwhJBpBdBC"},
{"name": "Love Removal Machine", "artists": ["The Cult"], "album": "Pure Cult", "duration": 258000, "link": "spotify:track:0pMvI3rFlzBBmOT1moPZ8K"},
{"name": "Rain", "artists": ["The Cult"], "album": "Pure Cult", "duration": 236000, "link": "spotify:track:1sFx6zGOMmrDcRgGPAgW4n"},
{"name": "Edie (Ciao Baby) (Edit)", "artists": ["The Cult"], "album": "Pure Cult", "duration": 242000, "link": "spotify:track:4wsxAIg1xAnhp5ckwrgtq7"},
{"name": "Wild Flower", "artists": ["The Cult"], "album": "Pure Cult", "duration": 217000, "link": "spotify:track:69b66xBvo7V3HYVTUGD81W"},
{"name": "Sweet Soul Sister (Edit)", "artists": ["The Cult"], "album": "Pure Cult", "duration": 209000, "link": "spotify:track:2cqklNuAzq6q6DBKNXSCxu"},
{"name": "Best Night", "artists": ["The War On Drugs"], "album": "Slave Ambient", "duration": 331000, "link": "spotify:track:4CM6rcCxRe9snF2ETtwSex"},
{"name": "Brothers", "artists": ["The War On Drugs"], "album": "Slave Ambient", "duration": 269000, "link": "spotify:track:0bchr5PjOKaJzMbw7D6S7V"},
{"name": "Baby Missiles", "artists": ["The War On Drugs"], "album": "Slave Ambient", "duration": 214000, "link": "spotify:track:071j0M72wZvQaNBN45onaM"},
{"name": "I Was There", "artists": ["The War On Drugs"], "album": "Slave Ambient", "duration": 230000, "link": "spotify:track:4xQt0l0bLbshMf8bOogDWD"},
{"name": "Your Love Is Calling My Name", "artists": ["The War On Drugs"], "album": "Slave Ambient", "duration": 361000, "link": "spotify:track:2Na3fvQyqr2pcR2xFjESZ3"},
{"name": "ICBYS", "artists": ["Zambri"], "album": "ICBYS", "duration": 269000, "link": "spotify:track:4G4tLhfawWJHNNK2onXgPq"},
{"name": "To Keep Back", "artists": ["Zambri"], "album": "Glossolalia", "duration": 287000, "link": "spotify:track:3dsHik6s3e1Vdn7qVpgIYW"},
{"name": "Clarity", "artists": ["John Mayer"], "album": "Heavier Things", "duration": 271000, "link": "spotify:track:6atVS7UZBxoyJkkteM62u5"},
{"name": "Bigger Than My Body", "artists": ["John Mayer"], "album": "Heavier Things", "duration": 266000, "link": "spotify:track:0Jh9EBGN205Yc7JN2zZ2f1"},
{"name": "How You Like Me Now", "artists": ["The Heavy"], "album": "Ninja Tune 17 Tracks", "duration": 217000, "link": "spotify:track:170JhN0I7D7LFekcGSJFOC"},
{"name": "Don't Know Why", "artists": ["Norah Jones"], "album": "Come Away With Me", "duration": 186000, "link": "spotify:track:6ybViy2qrO9sIi41EgRJgx"},
{"name": "Sunrise", "artists": ["Norah Jones"], "album": "Feels Like Home", "duration": 201000, "link": "spotify:track:7zkLpY72g6lKQbiHDqri1S"},
{"name": "Chasing Pirates", "artists": ["Norah Jones"], "album": "The Fall", "duration": 161000, "link": "spotify:track:7GsLrzsAash4bp75SltRaN"},
{"name": "Man Of The Hour", "artists": ["Norah Jones"], "album": "The Fall", "duration": 177000, "link": "spotify:track:2GEv0qEnkXg09cItFvk5bf"},
{"name": "Where Not To Look For Freedom", "artists": ["The Belle Brigade"], "album": "The Belle Brigade", "duration": 264000, "link": "spotify:track:5xU9jl7VEiVu3dD6Ezz2ev"},
{"name": "Lucky Guy", "artists": ["The Belle Brigade"], "album": "The Belle Brigade", "duration": 222000, "link": "spotify:track:4rIpwWK2TTZIW809zKZYm6"},
{"name": "Lonely Lonely", "artists": ["The Belle Brigade"], "album": "The Belle Brigade", "duration": 159000, "link": "spotify:track:6cPZefvhXnamOQ4RSliyfM"},
{"name": "My Goodness", "artists": ["The Belle Brigade"], "album": "The Belle Brigade", "duration": 178000, "link": "spotify:track:5yVexfvPVnByjLLgeUBYI9"},
{"name": "I Didn't Mean It", "artists": ["The Belle Brigade"], "album": "The Twilight Saga: Breaking Dawn - Part 1", "duration": 213000, "link": "spotify:track:6NG0uwFdLTtuQRBdl51CNx"},
{"name": "Losers", "artists": ["The Belle Brigade"], "album": "The Belle Brigade", "duration": 242000, "link": "spotify:track:5sl4ULweabby50v3S6khyf"},
{"name": "I Didn't Mean It - Vibey Version", "artists": ["The Belle Brigade"], "album": "The Twilight Saga: Breaking Dawn - Part 1", "duration": 193000, "link": "spotify:track:7Ma4XgLDtkEnP6q6Jn3YmN"},
{"name": "Sweet Louise", "artists": ["The Belle Brigade"], "album": "The Belle Brigade", "duration": 185000, "link": "spotify:track:3vSMaH0fcLIi2Cld5pEoGU"},
{"name": "Brave Man's Death", "artists": ["J Roddy Walston And The Business"], "album": "J Roddy Walston And The Business", "duration": 321000, "link": "spotify:track:57ShXATeiwxqyjDDE9nYyR"},
{"name": "Don't Break The Needle", "artists": ["J Roddy Walston And The Business"], "album": "J Roddy Walston And The Business", "duration": 169000, "link": "spotify:track:2VNmpB77YXrSPpqlsswsHt"},
{"name": "I Don't Wanna Hear It", "artists": ["J Roddy Walston And The Business"], "album": "HOPE Campaign Tribute Album 2010", "duration": 264000, "link": "spotify:track:1OtwWmXEFc3ZfYjpkb8Dd4"},
{"name": "Used To Did", "artists": ["J Roddy Walston And The Business"], "album": "J Roddy Walston And The Business", "duration": 238000, "link": "spotify:track:0531jjnciSmahK5dknvuOg"},
{"name": "Full Growing Man", "artists": ["J Roddy Walston And The Business"], "album": "J Roddy Walston And The Business", "duration": 245000, "link": "spotify:track:49152PAVcsAT2gQ1AzM74k"},
{"name": "Metal Man", "artists": ["Electric Eel Shock"], "album": "Sugoi Indeed", "duration": 201000, "link": "spotify:track:3jIAz4T7viTDU3qV7qBcyg"},
{"name": "Out Of Control", "artists": ["Electric Eel Shock"], "album": "Sugoi Indeed", "duration": 174000, "link": "spotify:track:7J8JADZyafN7e3mEiYt2zB"},
{"name": "Iron Man", "artists": ["Electric Eel Shock"], "album": "Beat Me", "duration": 265000, "link": "spotify:track:6My11dTDbTfC2uE7swCRjw"},
{"name": "Sugoi Indeed", "artists": ["Electric Eel Shock"], "album": "Sugoi Indeed", "duration": 177000, "link": "spotify:track:0McjYVt03Ox4YNsgIlxuzc"},
{"name": "Mr. Toat", "artists": ["Electric Eel Shock"], "album": "Sugoi Indeed", "duration": 223000, "link": "spotify:track:4DPvyAxBaeGWUjwcbEKAJ8"},
{"name": "Dancing With The DJ", "artists": ["The Knocks"], "album": "Dancing With The DJ", "duration": 235000, "link": "spotify:track:7LsAMq97fppoHHo4QNNCyl"},
{"name": "Make It Better", "artists": ["The Knocks"], "album": "Make It Better", "duration": 234000, "link": "spotify:track:5sbwbTMG9jY12MCu2wKLLM"},
{"name": "Magic", "artists": ["The Knocks", "Gary Go"], "album": "Magic", "duration": 246000, "link": "spotify:track:31Ypd8nIMj9TVxBYNp6LGS"},
{"name": "When You've Got Music", "artists": ["The Knocks"], "album": "Make It Better", "duration": 161000, "link": "spotify:track:61sVUaG3ymuNZ4Rcb3EOHy"},
{"name": "Carry The Zero", "artists": ["Built To Spill"], "album": "Keep It Like A Secret", "duration": 344000, "link": "spotify:track:3HMOMdRPywfouYx5B4PvaH"},
{"name": "Strange", "artists": ["Built To Spill"], "album": "Ancient Melodies Of The Future", "duration": 240000, "link": "spotify:track:27peQQXqMd8GHpFVRsvpoU"},
{"name": "Car", "artists": ["Built To Spill"], "album": "The Normal Years", "duration": 187000, "link": "spotify:track:3o66Ob6gxTrTXTv5tZZrw3"},
{"name": "Liar", "artists": ["Built To Spill"], "album": "You In Reverse", "duration": 311000, "link": "spotify:track:5EBDvc4cX8tqalRFGRwm7A"},
{"name": "Goin' Against Your Mind", "artists": ["Built To Spill"], "album": "You In Reverse", "duration": 522000, "link": "spotify:track:1rxz8AseGxCsYQDHyg4scv"},
{"name": "A Walk", "artists": ["Tycho"], "album": "Dive", "duration": 317000, "link": "spotify:track:5MSfgtOBZkbxlcwsI9XNpf"},
{"name": "Hours", "artists": ["Tycho"], "album": "Dive", "duration": 344000, "link": "spotify:track:2lQFc312TSd7oToBE8Btl1"},
{"name": "Daydream", "artists": ["Tycho"], "album": "Dive", "duration": 334000, "link": "spotify:track:3x1QE1uiG9wqYL7oBW4C8Z"},
{"name": "Dive", "artists": ["Tycho"], "album": "Dive", "duration": 500000, "link": "spotify:track:3VxLqVKyWp3KL0MTzZKUCM"},
]}
