{"playlist_name": "The Best of AM Gold on Popdose",
"http_link": "http://open.spotify.com/user/grayflannelsuit/playlist/0tiDCqr7Hwrb7BzXSQfCqE",
"spotify_link": "spotify:user:grayflannelsuit:playlist:0tiDCqr7Hwrb7BzXSQfCqE",
"songs": [
{"name": "My Girl", "artists": ["The Temptations"], "album": "Motown: The Complete No. 1's", "duration": 178000, "link": "spotify:track:2wz9T22pzkpKNuaWLBnY28"},
{"name": "Up On The Roof", "artists": ["The Drifters"], "album": "The Ultimate All-Time Greatest Collection", "duration": 151000, "link": "spotify:track:5PjMP0KT7jIS3zqUBrer6K"},
{"name": "When I Fall In Love", "artists": ["The Lettermen"], "album": "Capitol Collectors Series", "duration": 149000, "link": "spotify:track:49GPTzDeWp39GG6YhISiAx"},
{"name": "Surfer Girl (2001 Digital Remaster) (U.S. Version)", "artists": ["The Beach Boys"], "album": "The Beach Boys Classics...Selected By Brian Wilson", "duration": 149000, "link": "spotify:track:1hWb4kvjUTTmmQU1R65qo2"},
{"name": "The Girl From Ipanema", "artists": ["Stan Getz", "João Gilberto"], "album": "Getz/Gilberto", "duration": 325000, "link": "spotify:track:58TnktmMKygKvmKEHInhuc"},
{"name": "California Girls (Stereo)", "artists": ["The Beach Boys"], "album": "The Originals", "duration": 160000, "link": "spotify:track:1j1hPTCBdhROVexqMg5P0s"},
{"name": "You've Lost That Loving Feeling", "artists": ["The Righteous Brothers"], "album": "Doo Wop Golden Oldies Vol 3", "duration": 230000, "link": "spotify:track:60OSMN1IVbqHvOQQmmZ6Xm"},
{"name": "Love Letters", "artists": ["Ketty Lester"], "album": "100 Hits Of The Swingin' 60's", "duration": 161000, "link": "spotify:track:7utwO0OXDXxOXZN8kEibiO"},
{"name": "You've Really Got A Hold On Me", "artists": ["The Miracles"], "album": "Motown: The Complete No. 1's", "duration": 192000, "link": "spotify:track:141K1Yezgm4SglALjqbjA4"},
{"name": "The End Of The World", "artists": ["Skeeter Davis"], "album": "The Best Of Skeeter Davis", "duration": 156000, "link": "spotify:track:4Ya02upejdDxPbtHFJLNWR"},
{"name": "Our Day Will Come", "artists": ["Ruby And The Romantics"], "album": "The Very Best Of", "duration": 154000, "link": "spotify:track:6sbYrzvV5EDVWzBr6dvnMZ"},
{"name": "Hey Girl", "artists": ["Freddie Scott"], "album": "Lost Soul Gems", "duration": 191000, "link": "spotify:track:4pAF6aeCORaG6OQAgE9Vdf"},
{"name": "Two Lovers", "artists": ["Mary Wells"], "album": "Motown: The Complete No. 1's", "duration": 166000, "link": "spotify:track:0K2l6C93A8rwb6kfoa1vqU"},
{"name": "Crying In The Rain", "artists": ["The Everly Brothers"], "album": "The Golden Hits Of The Everly Brothers", "duration": 120000, "link": "spotify:track:3lWuagNhAzcqOikD5KnBku"},
{"name": "Since I Fell For You", "artists": ["Lenny Welch"], "album": "Soul Legend", "duration": 174000, "link": "spotify:track:3JHZP7LqzVWLbGapMEsaWd"},
{"name": "On Broadway", "artists": ["The Drifters"], "album": "The Rock 'n' Roll Era: 1963", "duration": 181000, "link": "spotify:local:The+Drifters:The+Rock+%27n%27+Roll+Era%3a+1963:On+Broadway:181"},
{"name": "Anyone Who Had A Heart", "artists": ["Dionne Warwick"], "album": "Anyone Who Had A Heart", "duration": 189000, "link": "spotify:track:2BQZvZsA9SRafvWEBSQnri"},
{"name": "Baby Love", "artists": ["The Supremes"], "album": "The Definitive Collection", "duration": 156000, "link": "spotify:track:7FkaVGxZhM0UA9frxbHPvD"},
{"name": "She's Not There", "artists": ["The Zombies"], "album": "The Original Studio Recordings", "duration": 144000, "link": "spotify:track:4EUtso2WpFvcgUCeF9Te8p"},
{"name": "Goin' Out Of My Head", "artists": ["Little Anthony & The Imperials"], "album": "60's Rock 'N' Roll - Tossin' And Turnin'", "duration": 151000, "link": "spotify:track:4QmqszFIOIrOziuexwILNd"},
{"name": "Walk On By - Live Version", "artists": ["Dionne Warwick"], "album": "Very Dionne", "duration": 183000, "link": "spotify:track:1mhjCOPmpt79wqrRPNdX9E"},
{"name": "Let It Be Me", "artists": ["Jerry Butler & Betty Everett"], "album": "Golden Hits forever V4", "duration": 172000, "link": "spotify:track:5g9gt2YgLMNDENdlKdV92v"},
{"name": "Wishin' And Hopin'", "artists": ["Dusty Springfield"], "album": "The Very Best Of Dusty Springfield", "duration": 176000, "link": "spotify:track:36iMcIUc4LZvjhrID5aiMl"},
{"name": "Under The Boardwalk - Single/LP Version", "artists": ["The Drifters"], "album": "Under The Boardwalk", "duration": 162000, "link": "spotify:track:65jrjEhWfAvysKfnojk1i0"},
{"name": "My Guy", "artists": ["Mary Wells"], "album": "Motown: The Complete No. 1's", "duration": 172000, "link": "spotify:track:5eQDErH4pyfb9ZhbyV53ly"},
{"name": "You Don't Own Me", "artists": ["Lesley Gore"], "album": "Her Very Best", "duration": 152000, "link": "spotify:track:5ILumokzwPbOjc78BovKEZ"},
{"name": "When I Grow Up (To Be A Man) [2001- Remaster] [Mono] [U.S. Version]", "artists": ["The Beach Boys"], "album": "The Very Best Of The Beach Boys: Sounds Of Summer", "duration": 124000, "link": "spotify:track:3aaz4mjJSUbupLQiYm1X03"},
{"name": "Downtown", "artists": ["Petula Clark"], "album": "Doo Wop Golden Oldies Vol 1", "duration": 194000, "link": "spotify:track:00cizc1Vk0iho4mhcMkOpn"},
{"name": "Do You Believe In Magic", "artists": ["The Lovin' Spoonful"], "album": "Playlist: The Very Best Of The Lovin' Spoonful", "duration": 125000, "link": "spotify:track:3WnvXncCC2nERn5myOmKdE"},
{"name": "Make Me Your Baby", "artists": ["Barbara Lewis"], "album": "Rhino Hi-Five: Barbara Lewis", "duration": 153000, "link": "spotify:track:1pCQWy9SzQNT9v4arSsqoT"},
{"name": "King Of The Road", "artists": ["Roger Miller"], "album": "Super Hits", "duration": 145000, "link": "spotify:track:59woCpyuR3BOYyseQHAAf0"},
{"name": "Back In My Arms Again", "artists": ["The Supremes"], "album": "The Definitive Collection", "duration": 174000, "link": "spotify:track:2p5261qgIgP4fEZW2P8QeR"},
{"name": "The Tracks Of My Tears", "artists": ["Smokey Robinson & The Miracles"], "album": "The Definitive Collection", "duration": 175000, "link": "spotify:track:7FwkoTz8Ic8C5YaE9XXGIU"},
{"name": "You Don't Have To Say You Love Me", "artists": ["Dusty Springfield"], "album": "40 Original Hits", "duration": 167000, "link": "spotify:track:2GleCQ0IwpYgDL5SBE57XN"},
{"name": "You Can't Hurry Love - Album Version (Stereo)", "artists": ["The Supremes"], "album": "The Supremes: Box Set", "duration": 167000, "link": "spotify:track:2BNP0fIRCHM2uDznRe6S7u"},
{"name": "I'm A Believer", "artists": ["The Monkees"], "album": "The Best Of The Monkees", "duration": 166000, "link": "spotify:track:1CSLeVCXmetBh8IkTPMFdL"},
{"name": "You Didn't Have To Be So Nice", "artists": ["The Lovin' Spoonful"], "album": "Playlist: The Very Best Of The Lovin' Spoonful", "duration": 147000, "link": "spotify:track:3GNPDi8igS9svIk2KRsdwN"},
{"name": "I Say A Little Prayer", "artists": ["Dionne Warwick"], "album": "Rhino Hi-Five: Dionne Warwick", "duration": 185000, "link": "spotify:track:13R7fXaes2QuvoppPOeTyc"},
{"name": "To Love Somebody", "artists": ["Bee Gees"], "album": "Best Of Bee Gees, Vol. 1", "duration": 182000, "link": "spotify:track:4eplXJXsYsNWdR5OdVWUiJ"},
{"name": "Tell It Like It Is", "artists": ["Aaron Neville"], "album": "Best of Aaron Neville", "duration": 182000, "link": "spotify:track:1bgoIr0DWWhoY9yUFo3VwX"},
{"name": "Different Drum", "artists": ["Stone Poneys"], "album": "Evergreen Vol.2", "duration": 160000, "link": "spotify:track:3k63RLvRgkgPGx0keOH3P6"},
{"name": "Ain't Nothing Like The Real Thing", "artists": ["Marvin Gaye", "Tammi Terrell"], "album": "The Very Best Of Marvin Gaye", "duration": 133000, "link": "spotify:track:5tyfoVBe0W0vfTLZrVFXCz"},
{"name": "I Wish It Would Rain", "artists": ["The Temptations"], "album": "Motown: The Complete No. 1's", "duration": 166000, "link": "spotify:track:2dQx3sIylsbvagZCNf69h4"},
{"name": "Wichita Lineman", "artists": ["Glen Campbell"], "album": "Wichita Lineman", "duration": 186000, "link": "spotify:track:6V9VCm1zOY2lGR80RehJ9i"},
{"name": "I Heard It Through The Grapevine", "artists": ["Marvin Gaye"], "album": "The Big Chill 15th Anniversary", "duration": 301000, "link": "spotify:track:4RBf7GeycUsElKFKW5SSyh"},
{"name": "[Sittin' On] The Dock Of The Bay", "artists": ["Otis Redding"], "album": "Atlantic 60th: Soul, Sweat And Strut", "duration": 164000, "link": "spotify:track:50uGbeaQIxKiSc7jvRTjWx"},
{"name": "Everybody's Talkin' (From \"Midnight Cowboy\")", "artists": ["Harry Nilsson;George Tipton"], "album": "Original Album Classics", "duration": 165000, "link": "spotify:track:12B10RuN7pKBCT9Hplq883"},
{"name": "Wedding Bell Blues", "artists": ["The Fifth Dimension"], "album": "Master Hits", "duration": 163000, "link": "spotify:track:1NmEZ3MPCktnLtrqusUrzt"},
{"name": "You Showed Me", "artists": ["The Turtles"], "album": "The Turtles Present The Battle of the Bands", "duration": 196000, "link": "spotify:track:7j1ABZOylWUPUIZTt5x6AL"},
{"name": "Your Song", "artists": ["Elton John"], "album": "Rocket Man: The Definitive Hits", "duration": 242000, "link": "spotify:track:6MwspV09vwHdLI6TV51rW6"},
{}]}
