{"playlist_name": "ShareMyPlaylists.com New Releases 2012",
"http_link": "http://open.spotify.com/user/sharemyplaylists.com/playlist/6OP8ZuclCQVuvvOJgEOcJm",
"spotify_link": "spotify:user:sharemyplaylists.com:playlist:6OP8ZuclCQVuvvOJgEOcJm",
"songs": [
{"name": "", "artists": ["Dunno yet."], "album": "Dunno yet.", "duration": 0, "link": "spotify:track:5g5L0YuCmSfM7LdnNRSuBv"},
{"name": "Let's Go feat. Ne-Yo - Radio Edit", "artists": ["Calvin Harris"], "album": "Let's Go feat. Ne-Yo", "duration": 226000, "link": "spotify:track:2XERAvP5rto44nAuJE2Rni"},
{"name": "", "artists": ["Dunno yet."], "album": "Dunno yet.", "duration": 0, "link": "spotify:track:0J4UpbKOPjbUNRwbzGl7Aw"},
{"name": "", "artists": ["Dunno yet."], "album": "Dunno yet.", "duration": 0, "link": "spotify:track:3P0kA2ZDmXPoEBnkz4CP1h"},
{"name": "", "artists": ["Dunno yet."], "album": "Dunno yet.", "duration": 0, "link": "spotify:track:0UoFrWtLKR3mkDeFzr8ZIH"},
{"name": "", "artists": ["Dunno yet."], "album": "Dunno yet.", "duration": 0, "link": "spotify:track:74sikPdkFndcbXztM9j8dD"},
{"name": "I Used To Have It All", "artists": ["Maverick Sabre"], "album": "Lonely Are The Brave", "duration": 231000, "link": "spotify:track:0xW5obn2tISw8ICScoXeG3"},
{"name": "", "artists": ["Dunno yet."], "album": "Dunno yet.", "duration": 0, "link": "spotify:track:69WWLAtHgjs5PI2iTM77TX"},
{"name": "", "artists": ["Dunno yet."], "album": "Dunno yet.", "duration": 0, "link": "spotify:track:2ntoNHeWpptMBx9Sbj4Vd2"},
{"name": "Sixteen Saltines", "artists": ["Jack White"], "album": "Blunderbuss", "duration": 157000, "link": "spotify:track:2GmMkODuUWlFZn87jdjbEy"},
{"name": "", "artists": ["Dunno yet."], "album": "Dunno yet.", "duration": 0, "link": "spotify:track:5ZOhKoqC0mqXmpBERIvxP3"},
{"name": "", "artists": ["Dunno yet."], "album": "Dunno yet.", "duration": 0, "link": "spotify:track:2JXBUoheyRbQefGUSmPgsl"},
{"name": "", "artists": ["Dunno yet."], "album": "Dunno yet.", "duration": 0, "link": "spotify:track:685I20she26iLv9CXsbgcq"},
{"name": "", "artists": ["Dunno yet."], "album": "Dunno yet.", "duration": 0, "link": "spotify:track:0uT4mkB7W2FU7tv6XP9qzU"},
{"name": "", "artists": ["Dunno yet."], "album": "Dunno yet.", "duration": 0, "link": "spotify:track:3oFDUfFa4V1O1daSsPkYJc"},
{"name": "", "artists": ["Dunno yet."], "album": "Dunno yet.", "duration": 0, "link": "spotify:track:4q8ebYdQeYgbga8hzGfVlX"},
{"name": "", "artists": ["Dunno yet."], "album": "Dunno yet.", "duration": 0, "link": "spotify:track:3FLHkXIsV2sfRbeUEs0lIo"},
{"name": "Can't Say No", "artists": ["Conor Maynard"], "album": "Can't Say No", "duration": 193000, "link": "spotify:track:0AHpuVdVEbQu8bzGUieSKi"},
{"name": "", "artists": ["Dunno yet."], "album": "Dunno yet.", "duration": 0, "link": "spotify:track:53QF56cjZA9RTuuMZDrSA6"},
{"name": "", "artists": ["Dunno yet."], "album": "Dunno yet.", "duration": 0, "link": "spotify:track:1QgyB1cfMP415DBQh6EK04"},
{"name": "", "artists": ["Dunno yet."], "album": "Dunno yet.", "duration": 0, "link": "spotify:track:2qTDX9vvhc4oQWqGCsFf5p"},
{"name": "", "artists": ["Dunno yet."], "album": "Dunno yet.", "duration": 0, "link": "spotify:track:3prlsnSDO9YY8Aa2W4k3np"},
{"name": "", "artists": ["Dunno yet."], "album": "Dunno yet.", "duration": 0, "link": "spotify:track:7dAqB8UPj51HdbVjQTGs8n"},
{"name": "", "artists": ["Dunno yet."], "album": "Dunno yet.", "duration": 0, "link": "spotify:track:2CJlJKDRC3QXz070NHwaQQ"},
{"name": "Primadonna", "artists": ["Marina and The Diamonds"], "album": "Primadonna", "duration": 221000, "link": "spotify:track:4lxGaohmC4i0Zlc5WFHxtO"},
{"name": "", "artists": ["Dunno yet."], "album": "Dunno yet.", "duration": 0, "link": "spotify:track:4Vb0dKRJMxggqh6CvElhep"},
{"name": "", "artists": ["Dunno yet."], "album": "Dunno yet.", "duration": 0, "link": "spotify:track:6p5s2eYaJj0tURET9uKxWL"},
{"name": "Settle Down", "artists": ["Kimbra"], "album": "Settle Down EP", "duration": 242000, "link": "spotify:track:4FULdw7r52SqgnhwRxf3NK"},
{"name": "", "artists": ["Dunno yet."], "album": "Dunno yet.", "duration": 0, "link": "spotify:track:1z7Cji0yJLNjZK4PAZIs8q"},
{"name": "", "artists": ["Dunno yet."], "album": "Dunno yet.", "duration": 0, "link": "spotify:track:1WpH3sPyvbTmb7IfS1JWfk"},
{"name": "", "artists": ["Dunno yet."], "album": "Dunno yet.", "duration": 0, "link": "spotify:track:32CS1c7IyC8jzeFs55Q9n4"},
{"name": "Boyfriend", "artists": ["Justin Bieber"], "album": "Boyfriend", "duration": 172000, "link": "spotify:track:1CnpZ2ANl5AStEnkXmiwCl"},
{"name": "Climax", "artists": ["Usher"], "album": "Climax", "duration": 234000, "link": "spotify:track:14dkdsZPn9MJmMEl0PETbu"},
{"name": "Hey Jane", "artists": ["Spiritualized"], "album": "Hey Jane", "duration": 534000, "link": "spotify:track:3G2eh98s3PL01N2EeCJHep"},
{"name": "", "artists": ["Dunno yet."], "album": "Dunno yet.", "duration": 0, "link": "spotify:track:0lXTIB6m6BOSmHkcxE2bhp"},
{"name": "", "artists": ["Dunno yet."], "album": "Dunno yet.", "duration": 0, "link": "spotify:track:6BFAlw8Ra5ZVY2FsRFSuKv"},
{"name": "", "artists": ["Dunno yet."], "album": "Dunno yet.", "duration": 0, "link": "spotify:track:3iYi8lSUeFufl1cB5ISFKu"},
{"name": "", "artists": ["Dunno yet."], "album": "Dunno yet.", "duration": 0, "link": "spotify:track:32fQTgM2Cfxubtt6CNA1uX"},
{"name": "", "artists": ["Dunno yet."], "album": "Dunno yet.", "duration": 0, "link": "spotify:track:5nyf8qg5e3N6mqGTBnfGxv"},
{"name": "", "artists": ["Dunno yet."], "album": "Dunno yet.", "duration": 0, "link": "spotify:track:54A1GL2zDaVzJHQ4j0G1xr"},
{"name": "", "artists": ["Dunno yet."], "album": "Dunno yet.", "duration": 0, "link": "spotify:track:315d6PpdKyTTS7jJPr2wQO"},
{"name": "", "artists": ["Dunno yet."], "album": "Dunno yet.", "duration": 0, "link": "spotify:track:144IDsvJGDt6onxuvG3bnP"},
{"name": "", "artists": ["Dunno yet."], "album": "Dunno yet.", "duration": 0, "link": "spotify:track:5aDTNRc30d33H3Dw35bsNf"},
{"name": "", "artists": ["Dunno yet."], "album": "Dunno yet.", "duration": 0, "link": "spotify:track:79F5OzSgfMKQEyjKSG45Hg"},
{"name": "Call Me Maybe", "artists": ["Carly Rae Jepsen"], "album": "Call Me Maybe", "duration": 194000, "link": "spotify:track:6HkNDcyWdnFXCBkDV5WXNO"},
{"name": "", "artists": ["Dunno yet."], "album": "Dunno yet.", "duration": 0, "link": "spotify:track:4NFd6jLN4MudNhul4U9WW5"},
{"name": "", "artists": ["Dunno yet."], "album": "Dunno yet.", "duration": 0, "link": "spotify:track:6AJM0aIljiUbWgxE86rjwK"},
{"name": "", "artists": ["Dunno yet."], "album": "Dunno yet.", "duration": 0, "link": "spotify:track:3NqSlxR8xMWxLeVonRKsTN"},
{"name": "Never Let Me Go", "artists": ["Florence + The Machine"], "album": "Ceremonials", "duration": 271000, "link": "spotify:track:3HNTLCpAGnizbyJmk7466r"},
{"name": "", "artists": ["Dunno yet."], "album": "Dunno yet.", "duration": 0, "link": "spotify:track:4zpIsZQUjysCVojH4khZj5"},
{"name": "", "artists": ["Dunno yet."], "album": "Dunno yet.", "duration": 0, "link": "spotify:track:3Z1ETggdKbMFbWs2PD44km"},
{"name": "", "artists": ["Dunno yet."], "album": "Dunno yet.", "duration": 0, "link": "spotify:track:1noRJ1qRDXxcfX8kwck1s2"},
{"name": "", "artists": ["Dunno yet."], "album": "Dunno yet.", "duration": 0, "link": "spotify:track:24aqDr55JwikqodjvobXJc"},
{"name": "", "artists": ["Dunno yet."], "album": "Dunno yet.", "duration": 0, "link": "spotify:track:4so7LwaIJ3Kp6rMrWkg2uI"},
{"name": "", "artists": ["Dunno yet."], "album": "Dunno yet.", "duration": 0, "link": "spotify:track:6MVm0FSNKbgJJHj3ujfn4b"},
{"name": "", "artists": ["Dunno yet."], "album": "Dunno yet.", "duration": 0, "link": "spotify:track:7bvQRVf1MA4xYZbiWMXbYQ"},
{"name": "", "artists": ["Dunno yet."], "album": "Dunno yet.", "duration": 0, "link": "spotify:track:2yoeDBgcxGeCmsUmSfVBT2"},
{"name": "", "artists": ["Dunno yet."], "album": "Dunno yet.", "duration": 0, "link": "spotify:track:3mDHy2rbplVQA4K03IniCM"},
{"name": "", "artists": ["Dunno yet."], "album": "Dunno yet.", "duration": 0, "link": "spotify:track:6Hm4CuNdxC7Hi7K9Ia9Lac"},
{"name": "", "artists": ["Dunno yet."], "album": "Dunno yet.", "duration": 0, "link": "spotify:track:0K0vIt3BmIiBvyKrcZ8uxq"},
{"name": "Turn Up The Music", "artists": ["Chris Brown"], "album": "Turn Up The Music", "duration": 229000, "link": "spotify:track:4x4RbsTuuqrmRoDFMyrhnA"},
{"name": "", "artists": ["Dunno yet."], "album": "Dunno yet.", "duration": 0, "link": "spotify:track:3dnDqcdJFXTXdcoHLn93WL"},
{"name": "", "artists": ["Dunno yet."], "album": "Dunno yet.", "duration": 0, "link": "spotify:track:436YBYrIqfY4IxoMA00vE9"},
{"name": "", "artists": ["Dunno yet."], "album": "Dunno yet.", "duration": 0, "link": "spotify:track:5JLv62qFIS1DR3zGEcApRt"},
{"name": "", "artists": ["Dunno yet."], "album": "Dunno yet.", "duration": 0, "link": "spotify:track:4g5188jUGQQHt5bqW7LshI"},
{"name": "", "artists": ["Dunno yet."], "album": "Dunno yet.", "duration": 0, "link": "spotify:track:2Vb61FWv1FRm4CbTTBfW2v"},
{"name": "", "artists": ["Dunno yet."], "album": "Dunno yet.", "duration": 0, "link": "spotify:track:1OdlBFp1SesiSjnanVPD7C"},
{"name": "", "artists": ["Dunno yet."], "album": "Dunno yet.", "duration": 0, "link": "spotify:track:1EEWEVpfp9gIQtT93OpOM7"},
{"name": "", "artists": ["Dunno yet."], "album": "Dunno yet.", "duration": 0, "link": "spotify:track:66jJyU8Hp3ddrl0Y5aGDMm"},
{"name": "212 - Clean Version", "artists": ["Azealia Banks", "Lazy Jay"], "album": "212", "duration": 206000, "link": "spotify:track:0cpIGzaR76yq210EMK5OOe"},
{"name": "", "artists": ["Dunno yet."], "album": "Dunno yet.", "duration": 0, "link": "spotify:track:6DrvIcSXNCB7vAGlafJLyC"},
{"name": "", "artists": ["Dunno yet."], "album": "Dunno yet.", "duration": 0, "link": "spotify:track:7nlHwvlptpiHWUP5D5TR4u"},
{"name": "", "artists": ["Dunno yet."], "album": "Dunno yet.", "duration": 0, "link": "spotify:track:5L4649QGihu5ev0woPI1R7"},
{"name": "Abraham's Daughter", "artists": ["Arcade Fire"], "album": "The Hunger Games: Songs From District 12 And Beyond", "duration": 202000, "link": "spotify:track:5CI295exWuUvBXBAl2mxUk"},
{"name": "Last Time", "artists": ["Labrinth"], "album": "Last Time", "duration": 264000, "link": "spotify:track:1fLk310TpqZ00AUB7rtEYs"},
{"name": "", "artists": ["Dunno yet."], "album": "Dunno yet.", "duration": 0, "link": "spotify:track:6f2xbwwZDzQnu0t6s9jxNH"},
{"name": "", "artists": ["Dunno yet."], "album": "Dunno yet.", "duration": 0, "link": "spotify:track:1rNKtCIxuVq5cAGm94FkW5"},
{"name": "", "artists": ["Dunno yet."], "album": "Dunno yet.", "duration": 0, "link": "spotify:track:4hsxfRX87ev9PJr7Q1r6Vk"},
{"name": "", "artists": ["Dunno yet."], "album": "Dunno yet.", "duration": 0, "link": "spotify:track:7B2QH4q9v4BjVJLEvMzUCn"},
{"name": "40 Mark Strasse", "artists": ["The Shins"], "album": "Port Of Morrow", "duration": 279000, "link": "spotify:track:5vEecM2EjGVW3YT6CdCjE3"},
{"name": "Part Of Me", "artists": ["Katy Perry"], "album": "Part Of Me", "duration": 215000, "link": "spotify:track:70nCWdRxSXHU3ZBUrPOJ7X"},
{"name": "", "artists": ["Dunno yet."], "album": "Dunno yet.", "duration": 0, "link": "spotify:track:41aZNnw779d8sN08DPSZqH"},
{"name": "She Doesn't Mind", "artists": ["Sean Paul"], "album": "She Doesn't Mind", "duration": 228000, "link": "spotify:track:3rt1J9ME2EHQDzx5vzqnVV"},
{"name": "", "artists": ["Dunno yet."], "album": "Dunno yet.", "duration": 0, "link": "spotify:track:7ksS2VMMt5ZDSpZOQTVj73"},
{"name": "", "artists": ["Dunno yet."], "album": "Dunno yet.", "duration": 0, "link": "spotify:track:48Vosc7jco7z6M3DuYxnuj"},
{"name": "", "artists": ["Dunno yet."], "album": "Dunno yet.", "duration": 0, "link": "spotify:track:4aY0tZIaboefmkBEsjAovI"},
{"name": "", "artists": ["Dunno yet."], "album": "Dunno yet.", "duration": 0, "link": "spotify:track:5StNU3F1203SjiB7RUKavv"},
{"name": "Greyhound", "artists": ["Swedish House Mafia"], "album": "Greyhound", "duration": 411000, "link": "spotify:track:3GC3xIxWImpR7dfv2F81ze"},
{"name": "", "artists": ["Dunno yet."], "album": "Dunno yet.", "duration": 0, "link": "spotify:track:6BmaLjU46be6fSI7xMCYQ3"},
{"name": "", "artists": ["Dunno yet."], "album": "Dunno yet.", "duration": 0, "link": "spotify:track:5945n6m4HeeB3MA40ojY7G"},
{"name": "", "artists": ["Dunno yet."], "album": "Dunno yet.", "duration": 0, "link": "spotify:track:2oYJ2NodN1uka2r06DRRXt"},
{"name": "", "artists": ["Dunno yet."], "album": "Dunno yet.", "duration": 0, "link": "spotify:track:3O92RJT1LgfNZ9S1X3tQE7"},
{"name": "", "artists": ["Dunno yet."], "album": "Dunno yet.", "duration": 0, "link": "spotify:track:43W1Vj5ReIhG5y6BwT7C8B"},
{"name": "", "artists": ["Dunno yet."], "album": "Dunno yet.", "duration": 0, "link": "spotify:track:4CLRwRrPnVmG5YDZA03G2H"},
{"name": "", "artists": ["Dunno yet."], "album": "Dunno yet.", "duration": 0, "link": "spotify:track:7eTDY2aiYel6i013RCWXpZ"},
{"name": "", "artists": ["Dunno yet."], "album": "Dunno yet.", "duration": 0, "link": "spotify:track:4Li2WHPkuyCdtmokzW2007"},
{"name": "", "artists": ["Dunno yet."], "album": "Dunno yet.", "duration": 0, "link": "spotify:track:01og3aEartwrOolgNCmvYV"},
{"name": "", "artists": ["Dunno yet."], "album": "Dunno yet.", "duration": 0, "link": "spotify:track:5MMW7zOn6BRwQbK0aT2JMZ"},
{"name": "", "artists": ["Dunno yet."], "album": "Dunno yet.", "duration": 0, "link": "spotify:track:3mr2iLJBPbDqAYKItgf4bu"},
{"name": "Elephant feat. Erick Morillo", "artists": ["Alexandra Burke"], "album": "Elephant feat. Erick Morillo", "duration": 231000, "link": "spotify:track:6Z0N3mEgzvTsQb40smVrvG"},
{"name": "", "artists": ["Dunno yet."], "album": "Dunno yet.", "duration": 0, "link": "spotify:track:5HPbLkSNQ3FIhfVu08rapq"},
{"name": "", "artists": ["Dunno yet."], "album": "Dunno yet.", "duration": 0, "link": "spotify:track:7nhoBXLcKtHu1ELMpca1xL"},
{"name": "", "artists": ["Dunno yet."], "album": "Dunno yet.", "duration": 0, "link": "spotify:track:5I2pryLKw0kmA41kEBBhFP"},
{"name": "", "artists": ["Dunno yet."], "album": "Dunno yet.", "duration": 0, "link": "spotify:track:7u0rneYVggOrHUUYbKQpUO"},
{"name": "", "artists": ["Dunno yet."], "album": "Dunno yet.", "duration": 0, "link": "spotify:track:2iGoyGCZcRDnBotIXq5fk8"},
{"name": "", "artists": ["Dunno yet."], "album": "Dunno yet.", "duration": 0, "link": "spotify:track:1FojyyJkR5jDWKqp7tmWXZ"},
{"name": "", "artists": ["Dunno yet."], "album": "Dunno yet.", "duration": 0, "link": "spotify:track:62Kq7uKXP7UTtFjdo9mXuP"},
{"name": "", "artists": ["Dunno yet."], "album": "Dunno yet.", "duration": 0, "link": "spotify:track:6pzIH8XaqIhdRvfuE8aVDn"},
{"name": "", "artists": ["Dunno yet."], "album": "Dunno yet.", "duration": 0, "link": "spotify:track:1BI9FjgnoU1uDBjEcVs3Y9"},
{"name": "Bright Lights", "artists": ["Tinchy Stryder", "Pixie Lott"], "album": "Bright Lights", "duration": 207000, "link": "spotify:track:1gyEW6IITaF83he1fL9xm3"},
{"name": "", "artists": ["Dunno yet."], "album": "Dunno yet.", "duration": 0, "link": "spotify:track:0amiYe9fVD2Q7sxcySivRG"},
{"name": "", "artists": ["Dunno yet."], "album": "Dunno yet.", "duration": 0, "link": "spotify:track:5yC6VMr5JcIJ5jHq9gcvwW"},
{"name": "", "artists": ["Dunno yet."], "album": "Dunno yet.", "duration": 0, "link": "spotify:track:39kr8Z8lf9vA5zjrcUAfiW"},
{"name": "", "artists": ["Dunno yet."], "album": "Dunno yet.", "duration": 0, "link": "spotify:track:7pFRv7A686A1pLCSYqLxDp"},
{"name": "", "artists": ["Dunno yet."], "album": "Dunno yet.", "duration": 0, "link": "spotify:track:4mKXUuDeq6whrGBVkcOeHs"},
{"name": "", "artists": ["Dunno yet."], "album": "Dunno yet.", "duration": 0, "link": "spotify:track:2fC8wtFFk6xBayMr2NqVgK"},
{"name": "", "artists": ["Dunno yet."], "album": "Dunno yet.", "duration": 0, "link": "spotify:track:5EbN9xKU8ag6pqTnH5zgVu"},
{"name": "", "artists": ["Dunno yet."], "album": "Dunno yet.", "duration": 0, "link": "spotify:track:2hraj96gK8dvCmjS8xOnK9"},
{"name": "", "artists": ["Dunno yet."], "album": "Dunno yet.", "duration": 0, "link": "spotify:track:6TKmvCPjB0jCETbkRMBRte"},
{"name": "", "artists": ["Dunno yet."], "album": "Dunno yet.", "duration": 0, "link": "spotify:track:2atYprr9JsQaLynGhrWhld"},
{"name": "", "artists": ["Dunno yet."], "album": "Dunno yet.", "duration": 0, "link": "spotify:track:0Vb0syD9pBA8m1xZ2dKvSV"},
{"name": "", "artists": ["Dunno yet."], "album": "Dunno yet.", "duration": 0, "link": "spotify:track:2eA160jLLoHiJKOqvOFKJt"},
{"name": "", "artists": ["Dunno yet."], "album": "Dunno yet.", "duration": 0, "link": "spotify:track:5nWSFDl55FXeMJWTnEtvMV"},
{"name": "Ray Charles", "artists": ["Chiddy Bang"], "album": "Ray Charles", "duration": 223000, "link": "spotify:track:3oIGAhEKVF2Cs1yzQvBNb2"},
{"name": "Icarus - Extended Mix", "artists": ["Madeon"], "album": "Icarus", "duration": 250000, "link": "spotify:track:3BwVwNRyBGyWTPNz794yG1"},
{"name": "Rockstar", "artists": ["Brian May", "Dappy"], "album": "Rockstar", "duration": 217000, "link": "spotify:track:4JpRKPtCIhCjw6evuY1pnt"},
{"name": "Lost Time", "artists": ["Javeon McCarthy"], "album": "Lost Time", "duration": 193000, "link": "spotify:track:47Qt4e7yrLXCkqIL4vz2Ez"},
{"name": "Skyscraper", "artists": ["Demi Lovato"], "album": "Skyscraper", "duration": 222000, "link": "spotify:track:2mrbEQOtsP73M2GWsfYzqW"},
{"name": "Ending Before I Begin", "artists": ["Darren Hayes"], "album": "Bloodstained Heart", "duration": 237000, "link": "spotify:track:0jTGha5VMzJ9yzV1pBel41"},
{"name": "Roman Reloaded - Explicit Version", "artists": ["Nicki Minaj", "Lil Wayne"], "album": "Roman Reloaded", "duration": 196000, "link": "spotify:track:1uxOhrDrGQlEunGZJcS78f"},
{"name": "DJ Ease My Mind - Radio Edit", "artists": ["Niki & The Dove"], "album": "DJ Ease My Mind", "duration": 202000, "link": "spotify:track:2Lh1hK3SvBll8UiU2RCNvM"},
{"name": "Black White & Blue", "artists": ["Ladyhawke"], "album": "Black White & Blue", "duration": 235000, "link": "spotify:track:6SCMiEOb9gZe3Rsi8wzGNv"},
{"name": "Days", "artists": ["The Drums"], "album": "Days", "duration": 269000, "link": "spotify:track:1HWxu2ZwIfxrnzZjvFMQTe"},
{"name": "Hey Jane", "artists": ["Spiritualized"], "album": "Hey Jane", "duration": 534000, "link": "spotify:track:3G2eh98s3PL01N2EeCJHep"},
{"name": "The Wolves - Acoustic", "artists": ["Ben Howard"], "album": "The Wolves", "duration": 337000, "link": "spotify:track:0iIleIbivvzkg3c6IadQGK"},
{"name": "Conduct", "artists": ["The Cranberries"], "album": "Roses", "duration": 310000, "link": "spotify:track:1ZD64c5p9ZcMEBTElfl4Kb"},
{"name": "Breathing - JRMX Club Mix", "artists": ["Jason Derulo"], "album": "Breathing", "duration": 470000, "link": "spotify:track:0MXIg5BjC2FaAnfGv2FTno"},
{"name": "The Wolf Is Getting Married", "artists": ["Sinead O’Connor"], "album": "How About I Be Me (And You Be You)?", "duration": 260000, "link": "spotify:track:34wfNvk8MmTsvmIIzcDW4t"},
{"name": "Fall From Grace", "artists": ["Meat Loaf"], "album": "Hell In A Handbasket", "duration": 227000, "link": "spotify:track:6HwUkCN4bfGRxWg3LI9Pd4"},
{"name": "Tonight", "artists": ["Saint Etienne"], "album": "Tonight", "duration": 278000, "link": "spotify:track:2oDGn5dVPALNSAF4XLDOvM"},
{"name": "Starships - Explicit Version", "artists": ["Nicki Minaj"], "album": "Starships", "duration": 211000, "link": "spotify:track:5VpmCqOpS4lgZODFhJiI8B"},
{"name": "Want U Back feat. Astro", "artists": ["Cher Lloyd"], "album": "Want U Back feat. Astro", "duration": 224000, "link": "spotify:track:5YWtklNg0WusNtUdDDH4wH"},
{"name": "Affairs Of The Heart", "artists": ["Damian "Jr. Gong" Marley"], "album": "Affairs Of The Heart", "duration": 240000, "link": "spotify:track:17PfXZ4eYQDZPXNKSNcfck"},
{"name": "Peso", "artists": ["A$AP Rocky"], "album": "Peso", "duration": 170000, "link": "spotify:track:5sl2735QKaOmL8UL4Q39Ut"},
{"name": "Narcotic Farm - Actress's Mad House Mix", "artists": ["Kasabian"], "album": "Goodbye Kiss", "duration": 227000, "link": "spotify:track:0PsZpTjLfOPh5gAmCe5AgD"},
{"name": "Mrs. Right", "artists": ["Mindless Behavior", "Chipmunk"], "album": "Mrs. Right", "duration": 249000, "link": "spotify:track:6wkc5Orj9DRfj7One39DS2"},
{"name": "Drunk - Lazy Jay's Wasted In London Remix", "artists": ["Ed Sheeran"], "album": "Drunk", "duration": 319000, "link": "spotify:track:1CXWkEskDfpBWfdyRL4u5G"},
{"name": "These Days", "artists": ["Foo Fighters"], "album": "Wasting Light", "duration": 298000, "link": "spotify:track:2kN05N1AQQplsgFweFAqYb"},
{"name": "Written On The Forehead", "artists": ["PJ Harvey"], "album": "Let England Shake", "duration": 220000, "link": "spotify:track:16LJY6mGHr0fB8qaRBvq0W"},
{"name": "Crush", "artists": ["Sleigh Bells"], "album": "Reign of Terror", "duration": 200000, "link": "spotify:track:3vBCYTfc1r2aeZAwJ87j8c"},
{"name": "Close to Nowhere", "artists": ["Band Of Skulls"], "album": "Sweet Sour", "duration": 272000, "link": "spotify:track:7E9l2zNreRWSJNm1Ly6r0c"},
{"name": "Maths - Original Mix", "artists": ["Deadmau5"], "album": "Maths", "duration": 413000, "link": "spotify:track:4ltiRbT7WBdCIKI4vdeiM5"},
{"name": "Ass Back Home - feat. Neon Hitch", "artists": ["Gym Class Heroes"], "album": "Ass Back Home", "duration": 222000, "link": "spotify:track:36zeiqHXQgO6ziYZUKKUn5"},
{"name": "All Is Said", "artists": ["Matt Cardle"], "album": "Amazing", "duration": 235000, "link": "spotify:track:1npFdfoZuiL1ePtyClnMcF"},
{"name": "The Last Goodbye", "artists": ["The Kills"], "album": "The Last Goodbye", "duration": 219000, "link": "spotify:track:7GfjP8KbOZQJSICuE9OxNZ"},
{"name": "Next to Me", "artists": ["Emeli Sandé"], "album": "Next to Me", "duration": 197000, "link": "spotify:track:5VHuGRvkB61pvdQjAgUazm"},
{"name": "In The End", "artists": ["Snow Patrol"], "album": "In The End", "duration": 241000, "link": "spotify:track:6rlCviXrcp1XYa931aniEW"},
{"name": "Does Anybody Care About Us?", "artists": ["The King Blues"], "album": "Does Anybody Care About Us?", "duration": 216000, "link": "spotify:track:72JUPiIGwRA3Vu40CarIXr"},
{"name": "Reckless With Your Love - Paul Epworth Radio Edit", "artists": ["Azari & III"], "album": "Reckless With Your Love", "duration": 196000, "link": "spotify:track:2dhqawz94P1hCwtSZiEYJz"},
{"name": "Sleeping In The Woods", "artists": ["Midnight Lion"], "album": "Sleeping In The Woods EP", "duration": 269000, "link": "spotify:track:2mY4gHGzANYxeOxDLG7vZk"},
{"name": "Pixelated People", "artists": ["Jess Mills"], "album": "Pixelated People", "duration": 225000, "link": "spotify:track:5cHDmXhfsqIY7F72msxpK9"},
{"name": "One Thing", "artists": ["One Direction"], "album": "One Thing", "duration": 197000, "link": "spotify:track:145CFE56P0HOkYt3rTfwzf"},
{"name": "Give Me All Your Luvin'", "artists": ["Madonna", "Nicki Minaj", "M.I.A."], "album": "Give Me All Your Luvin'", "duration": 202000, "link": "spotify:track:2SVtWaGAbJI7RFf7g1tJva"},
{"name": "No One", "artists": ["Maverick Sabre"], "album": "No One", "duration": 215000, "link": "spotify:track:5jwBi4knn98hrFM0VqBwMf"},
{"name": "Somebody That I Used To Know", "artists": ["Gotye", "Kimbra"], "album": "Somebody That I Used To Know", "duration": 245000, "link": "spotify:track:72Bd8uYIcYxUwtG8pyWf2P"},
{"name": "Pray To Be Free", "artists": ["James Levy And The Blood Red Rose"], "album": "Sneak Into My Room EP", "duration": 261000, "link": "spotify:track:5vOoTdlAqrHTBMzIZtI7s9"},
{"name": "T.H.E (The Hardest Ever) - Explicit Version", "artists": ["will.i.am", "Jennifer Lopez", "Mick Jagger"], "album": "T.H.E (The Hardest Ever)", "duration": 289000, "link": "spotify:track:2PpFFAqVL3tfLcDIaezPod"},
{"name": "Masterpiece", "artists": ["Madonna"], "album": "W.E. - Music From The Motion Picture", "duration": 239000, "link": "spotify:track:5AvJbuSAzUKWx5M3Mtr24L"},
{"name": "Mirror", "artists": ["Lil Wayne", "Bruno Mars"], "album": "Tha Carter IV", "duration": 228000, "link": "spotify:track:05pdoheuKPSotkjMgIVX6I"},
{"name": "Wings", "artists": ["Ringo Starr"], "album": "Ringo 2012", "duration": 211000, "link": "spotify:track:11defwQ2YTS6ZUaBD2SOGl"},
{"name": "On'n'On - Ruined by Rick Rubin", "artists": ["Justice"], "album": "On'n'On EP", "duration": 238000, "link": "spotify:track:3uDDTNatILGLzZRJIZ9pok"},
{"name": "Hail Bop", "artists": ["Django Django"], "album": "Django Django", "duration": 244000, "link": "spotify:track:2NpBn0EEaggby4UETK47tk"},
{"name": "Bear Hug", "artists": ["The 2 Bears"], "album": "Be Strong", "duration": 246000, "link": "spotify:track:5Xc0N7o6JNUhrHi7ultPZS"},
{"name": "Faded", "artists": ["Tyga", "Lil Wayne"], "album": "Faded", "duration": 213000, "link": "spotify:track:7Irp5B9hUwbLQ1bSOJhxoa"},
{"name": "Oh! - Original", "artists": ["Beardyman", "Foreign Beggars"], "album": "Oh!", "duration": 222000, "link": "spotify:track:5VIUsupzyAtx2RrwMCTT6e"},
{"name": "Borders", "artists": ["Feeder"], "album": "Borders", "duration": 212000, "link": "spotify:track:1GE7ULH75ujVK1MwfAGWhd"},
{"name": "Dark Horses", "artists": ["Hoodlums"], "album": "Dark Horses /Ends of the Earth", "duration": 246000, "link": "spotify:track:2e5gFVzVAg7MSkvSLtHzdZ"},
{"name": "Born To Die", "artists": ["Lana Del Rey"], "album": "Born To Die", "duration": 286000, "link": "spotify:track:6eFmEwPGFlSSau4yMUEaqN"},
{"name": "We Take Care Of Our Own", "artists": ["Bruce Springsteen"], "album": "We Take Care Of Our Own", "duration": 234000, "link": "spotify:track:3dKRiSSvLSdOv2dwzgCdu8"},
{"name": "Get Out My Head", "artists": ["Redlight"], "album": "Get Out My Head", "duration": 225000, "link": "spotify:track:1LC6p9xSpZBogQMqlWZ5SZ"},
{"name": "Twilight", "artists": ["Cover Drive"], "album": "Twilight", "duration": 209000, "link": "spotify:track:4dGf6OnNrGBfLt8dsnl05Z"},
{"name": "Darkness", "artists": ["Leonard Cohen"], "album": "Darkness", "duration": 269000, "link": "spotify:track:2LPJwJ07YqNbDiTstqIYmZ"},
{"name": "Bruised Orange (Chain Of Sorrow)", "artists": ["Bon Iver"], "album": "Towers", "duration": 241000, "link": "spotify:track:3Qs2VeTLcMrC6uV6aWeu2O"},
{"name": "Dark Matar", "artists": ["X-Press 2"], "album": "The House Of X-Press 2", "duration": 290000, "link": "spotify:track:5PcxE5FojczfLOboINJfGi"},
{"name": "We Never Win", "artists": ["Whales In Cubicles"], "album": "We Never Win", "duration": 214000, "link": "spotify:track:1hU2f3ldl36SF2IUsx0LlK"},
{"name": "The One That Got Away (Acoustic)", "artists": ["Katy Perry"], "album": "The One That Got Away (Acoustic)", "duration": 259000, "link": "spotify:track:7CBvEVJupaJ3Qmwx7i98Jp"},
{"name": "Shake Off The Curse", "artists": ["Pulled Apart By Horses"], "album": "Tough Love", "duration": 174000, "link": "spotify:track:1tUYet7Ap6QZeCkVAuwWJD"},
{"name": "Never Be a Right Time (Drums of London Remix)", "artists": ["Professor Green"], "album": "Never Be a Right Time", "duration": 221000, "link": "spotify:track:6WM5d9pSTanacemLNMfXya"},
{"name": "Percussion Map (Pt. 1)", "artists": ["DJ Food"], "album": "The Search Engine", "duration": 199000, "link": "spotify:track:2z9qtYPHY2ecXiybPPeFUO"},
{"name": "Boom Blast", "artists": ["Wiley"], "album": "Boom Blast", "duration": 215000, "link": "spotify:track:22sb98MFOPT3JZIHOQbGJK"},
{"name": "Antidote", "artists": ["Swedish House Mafia", "Knife Party"], "album": "Antidote", "duration": 374000, "link": "spotify:track:0hM7sJjGQQjQrQ6BeQpG7r"},
{"name": "Search Party", "artists": ["Enter Shikari"], "album": "A Flash Flood Of Colour", "duration": 246000, "link": "spotify:track:1oqds54H1KMZXyMUtRPe67"},
{"name": "Tattoo", "artists": ["Van Halen"], "album": "Tattoo", "duration": 283000, "link": "spotify:track:2gxzfUwmZANcpGGeHMpWBr"},
{"name": "Hit The Ground (Superman)", "artists": ["The Big Pink"], "album": "Future This", "duration": 296000, "link": "spotify:track:1QF4GgRZnVwaZBi6iYbSfC"},
{"name": "Sweetest Thing", "artists": ["The Rifles"], "album": "Sweetest Thing", "duration": 215000, "link": "spotify:track:5BpZhfV0WBuotQCExW7is6"},
{"name": "No Light, No Light", "artists": ["Florence + The Machine"], "album": "No Light, No Light", "duration": 275000, "link": "spotify:track:6jjlrReQgbfQ4lXrgJF9aB"},
{"name": "Simple Song", "artists": ["The Shins"], "album": "Simple Song", "duration": 256000, "link": "spotify:track:3jRHAsjvnSTmB5crrpqyTj"},
{"name": "Hang It Up", "artists": ["The Ting Tings"], "album": "Hang It Up", "duration": 191000, "link": "spotify:track:6RH3jNZL6qo5e0F6FyUQqJ"},
{"name": "Melancholy Sky (Original Mix)", "artists": ["Goldfrapp"], "album": "Melancholy Sky", "duration": 270000, "link": "spotify:track:34xc37MFF7xl3Ov4TiNSMV"},
{"name": "Feel To Follow", "artists": ["The Maccabees"], "album": "Given To The Wild", "duration": 209000, "link": "spotify:track:0ELy7mc6bdrfoxBMQhAEBT"},
{"name": "Bears", "artists": ["The Carpels"], "album": "Bears", "duration": 170000, "link": "spotify:track:7bzqIhGrZIsELYMO5NtmRM"},
{"name": "Do It Our Way - Play", "artists": ["Alesha Dixon"], "album": "Do It Our Way", "duration": 194000, "link": "spotify:track:3I3gQ8oOfXy134YwZiHDEU"},
{"name": "Yo-yo - Clean Radio Mix", "artists": ["Nicola Roberts"], "album": "Yo-yo", "duration": 204000, "link": "spotify:track:4KrcbaHznQGbQ2ysE4D6va"},
{"name": "Seven Stars", "artists": ["Air"], "album": "Seven Stars - Single", "duration": 266000, "link": "spotify:track:5INBk67dJVmrHaMoFF0F0t"},
{"name": "Stupid Hoe - Edited Version", "artists": ["Nicki Minaj"], "album": "Stupid Hoe", "duration": 197000, "link": "spotify:track:2i341tgy1FG0GjtYIuuXq3"},
{"name": "Immigrant Song", "artists": ["Trent Reznor", "Atticus Ross", "Karen O"], "album": "The Girl With the Dragon Tattoo", "duration": 168000, "link": "spotify:track:1EJAfK7kiDSA49O8t97M6v"},
{"name": "Staircase", "artists": ["Radiohead"], "album": "The Daily Mail & Staircase", "duration": 272000, "link": "spotify:track:5orR8ol81J6EYiaj1ET7NZ"},
{"name": "Summit - feat. Ellie Goulding", "artists": ["Skrillex"], "album": "Bangarang EP", "duration": 374000, "link": "spotify:track:1SbqxemPdwGlvmirtQVkCU"},
{"name": "If I Had A Gun...", "artists": ["Noel Gallagher's High Flying Birds"], "album": "If I Had A Gun...", "duration": 249000, "link": "spotify:track:5GUyvrNb71kRi3D65gg2pK"},
{"name": "Troublemaker", "artists": ["Taio Cruz"], "album": "Troublemaker", "duration": 221000, "link": "spotify:track:0UhKIv7aH1hHxTHWmsPJub"},
{"name": "You Da One", "artists": ["Rihanna"], "album": "Talk That Talk", "duration": 200000, "link": "spotify:track:1tavCgMGH7fnqcHeHGHi7I"},
{"name": "Leave It - Acoustic", "artists": ["Bombay Bicycle Club"], "album": "Leave It", "duration": 172000, "link": "spotify:track:29FX79Fy3H97GipTdbINre"},
{"name": "Do You Feel What I Feel?", "artists": ["JLS"], "album": "Do You Feel What I Feel?", "duration": 194000, "link": "spotify:track:71TApBHKBakqjDWgMIDB2P"},
{"name": "Give It All Back", "artists": ["Noah And The Whale"], "album": "Last Night On Earth", "duration": 176000, "link": "spotify:track:28naLTqOGvYYwTB9uGJdYN"},
]}
